Workbook

Sheet Start Here
A1: AI Security Risk Workbook v3.0
A3: One workbook that holds your organization's AI risk program: who you are and what you own (Org Profile), how tools are classified (Tool Function Mapping), the controls you expect at each risk level (Guardrail Checklist), the intake a requester fills in, the registers you keep (Tool Registry, Exception Tracker), the vendor landscape for picking tools, and the compliance mapping that ties every guardrail to the frameworks you answer to. The companion skill, ai-tool-risk-assessment, reads this workbook and produces one AI Risk Assessment Record per request.
A5: Cream cells | B5: Yours to fill in or change. Many arrive with a starter value; change only what differs at your organization.
A6: Rose cells | B6: Do not edit. Column A holds the keys the skill reads, and the other rose cells are calculated.
A7: Risk and family colors | B7: Low is sage green, Medium pale yellow, High apricot, Severe terracotta. Each of the seven families keeps one muted hue across every tab. Agentic rows are lavender.
A8: Data classes | B8: Four data classes, fixed across the workbook: Public (Low), Internal (Medium), Confidential (High), Restricted (Severe: PII, PHI, payment, export-controlled or other regulated data, and data about minors). Used as written on the intake, the registry and every record.
A10: 1. The tabs
A11: # | B11: Tab | C11: What it holds | D11: When you use it
A12: 1 | B12: =HYPERLINK("#'Org Profile'!A1","Org Profile") -> Org Profile | C12: Who you are, your governance routing, the tools you own (one or more per family), the program rules every tool is held to, how records look | D12: Fill it in once. Every record reads it.
A13: 2 | B13: =HYPERLINK("#'Tool Function Mapping'!A1","Tool Function Mapping") -> Tool Function Mapping | C13: The seven risk factors with their four levels, and 57 functions mapped to a risk level, the agentic flag, the guardrails each function requires and their families | D13: Classify a tool and list its functions; the functions decide the guardrails. Add functions of your own at the bottom.
A14: 3 | B14: =HYPERLINK("#'Guardrail Checklist'!A1","Guardrail Checklist") -> Guardrail Checklist | C14: 65 guardrails across seven families, each with the rule that puts it in scope (every tool, vendor products, or the functions that name it), the agentic flag, what to verify, what evidence proves it, and the control of yours that meets it | D14: The control library. The record lists the required guardrails at issue with their owner and control; the Verification sheet checks them after deployment.
A15: 4 | B15: =HYPERLINK("#'Intake Form'!A1","Intake Form") -> Intake Form | C15: A request form that is multiple choice wherever the answer has a fixed shape: the tool, how it will be used, vendor documents, and the questions an internal build has to answer | D15: Copy it per request, or hand out the standalone file.
A16: 5 | B16: =HYPERLINK("#'Tool Registry'!A1","Tool Registry") -> Tool Registry | C16: Living inventory of AI tools with risk, owners, status and review dates | D16: Keep it current. Never delete a row; mark it Decommissioned.
A17: 6 | B17: =HYPERLINK("#'Exception Tracker'!A1","Exception Tracker") -> Exception Tracker | C17: Exceptions for Severe-risk tools, guardrail deviations, emergency use, pilots and model versions, with renewals | D17: Whenever a tool runs outside policy for a time.
A18: 7 | B18: =HYPERLINK("#'AI Security Tool Landscape'!A1","AI Security Tool Landscape") -> AI Security Tool Landscape | C18: The seven families and about 100 vendors mapped to primary, secondary and tertiary families, refreshed October 2026 | D18: Picking a tool for a family you have no coverage in. A showcase, not a shortlist.
A19: 8 | B19: =HYPERLINK("#'Compliance Mapping'!A1","Compliance Mapping") -> Compliance Mapping | C19: Every guardrail mapped to CSA AICM, the EU AI Act, ISO/IEC 42001, MITRE ATLAS, NIST AI RMF, NIST AI 600-1, OWASP and SOC 2 | D19: Audit evidence, and the citations the Verification sheet carries.
A21: 2. How a request runs
A22: Step | B22: What happens
A23: 1. Intake | B23: The requester fills the Intake Form, or answers the same questions in chat. The tool name and the kind of request are the only required answers.
A24: 2. Research or discovery | B24: A vendor product is researched from its trust center, ISO/IEC 42001 certificate, AI terms, DPA and documentation. A vendor adding AI to a product you already use starts from the existing registry entry and what changed. An internal build has no public pages, so the engineering owner answers section 4 of the intake.
A25: 3. Classify and threat model | B25: Score the seven risk factors on the Tool Function Mapping tab. The highest factor sets the level. Any autonomous action sets the agentic flag. List the functions the tool performs. Walk STRIDE and the lethal trifecta against the tool.
A26: 4. Required guardrails | B26: The required list is the union of what the tool's functions require, plus the Guardrail Checklist rows marked Every tool (the program's own steps) and, for anything bought, Vendor products. The risk level routes the decision; it does not add guardrails. Each line carries its owner (the vendor, you, or both) and the control that meets it: the vendor's feature or your own tool from Org Profile section 3 and the Guardrail Checklist tab. A guardrail nothing meets is a Gap, and every Gap is a finding.
A27: 5. Issue and decide | B27: The record is issued with its open items (gaps, unknowns, findings due before a decision, questions outstanding) and a blank decision block. It drafts up to four questions for the vendor or the requester, only where an answer would move a risk factor. The approver the Org Profile names for the level records the decision, its conditions and the risk acceptance in the record itself.
A28: 6. Register | B28: The approved tool goes on the Tool Registry with its review cadence. Anything running outside policy goes on the Exception Tracker.
A29: 7. Verify after deployment | B29: Once the tool is live, the verifier walks the Verification sheet in the record file, collects the evidence for each required guardrail and marks Pass or Fail. Security approved the tool with guardrails; this is where it confirms they were put in place.
A31: 3. Risk levels at a glance
A32: Read from Org Profile section 2. Change them there.
A33: Risk level | B33: Approved by | C33: Reviewed | D33: Residual risk accepted by
A34: Low | B34: ='Org Profile'!C28 -> Security reviewer | C34: ='Org Profile'!C32 -> Yearly | D34: ='Org Profile'!C36 -> The business owner of the use case
A35: Medium | B35: ='Org Profile'!C29 -> Department lead with security review | C35: ='Org Profile'!C33 -> Every six months | D35: ='Org Profile'!C36 -> The business owner of the use case
A36: High | B36: ='Org Profile'!C30 -> AI governance committee | C36: ='Org Profile'!C34 -> Quarterly | D36: ='Org Profile'!C37 -> The business unit head
A37: Severe | B37: ='Org Profile'!C31 -> Exception only: CISO and the committee, with an executive sponsor | C37: ='Org Profile'!C35 -> Monthly | D37: ='Org Profile'!C38 -> A named executive, with the exception on record
A39: 4. Version history
A40: Version | B40: Date | C40: Changes
A41: v3.0 | B41: 2026-10-14 | C41: Rebuilt in the program-workbook layout: Org Profile with keys the skill reads, the function and guardrail libraries as tables, a multiple-choice intake that handles vendor products, vendor-added AI and internal builds, the registry and exception tracker kept with small updates, a refreshed landscape (about 100 vendors, statuses through September 2026), and a compliance mapping of every guardrail to eight framework columns with no blank cells. Four fixed data classes. One or more tools per guardrail. Guardrails are required by the functions a tool performs, plus a short every-tool baseline, rather than by risk level. Added two agentic guardrails (agent behavior monitoring, agent memory protection). Records are issued as the security team's assessment with a blank decision block for the approver, list required guardrails with owner, status and control, map the organization's tools against the tool's functions, and carry a Verification sheet for the manual check after deployment and a Coverage data sheet for the program metrics. Program Metrics, User Guide and Governance Guide retired; their settings moved into Org Profile.
A42: v2.0 | B42: 2026-04-23 | C42: 57 functions, 63 guardrails with agentic dual-tagging, 88 vendors, 21 compliance frameworks, muted palette.
A43: v1.3 | B43: 2026-02 | C43: 17 new vendors, 6 agentic guardrails, 4 new functions, updated mappings.
A44: v1.0 | B44: 2025-01 | C44: Initial release: 58 vendors, 40 guardrails, 41 functions.
A46: Last updated 2026-10-14. Owner: your security and risk function (edit on the Org Profile tab). Copyright 2026 Jason Robbins. Licensed under the Apache License, Version 2.0; the LICENSE and NOTICE files travel with the workbook. Vendor and product names identify products and do not imply endorsement.

Sheet Org Profile
A1: AI Security Risk Workbook: Org Profile
A3: Start here. This tab is what makes every assessment yours: your context, your routing, the tools you already own and the rules every new tool is held to. Fill it in once and keep it current. The skill reads it by the keys in column A, never by position, so you can add rows and reorder sections.
A5: Cream cells | B5: Yours to fill in. Pick from the list where a cell has one, and write None or Unknown where that is the honest answer.
A6: Rose cells | B6: Do not edit. Column A holds the keys the skill reads. Copy the key when you add a row of the same kind.
A7: Completion | B7: =IF((58-COUNTA(C11,C12,C13,C14,C15,C16,C17,C18,C19,C24,C25,C26,C27,C28,C29,C30,C31,C32,C33,C34,C35,C36,C37,C38,C39,C40,C41,C42,C43,C44,C45,C46,C51,C52,C53,C54,C55,C56,C57,C58,C59,C60,C61,C62,C63,C64,C65,C66,C67,C68,C69,C74,C75,C76,C77,C78,C83,C84))=0,"Complete: every answer the skill needs is filled in.","Still open: "&(58-COUNTA(C11,C12,C13,C14,C15,C16,C17,C18,C19,C24,C25,C26,C27,C28,C29,C30,C31,C32,C33,C34,C35,C36,C37,C38,C39,C40,C41,C42,C43,C44,C45,C46,C51,C52,C53,C54,C55,C56,C57,C58,C59,C60,C61,C62,C63,C64,C65,C66,C67,C68,C69,C74,C75,C76,C77,C78,C83,C84))&" of 58 answers. The skill stops and asks for them before it assesses anything. Section 6 has working defaults.") -> Still open: 36 of 58 answers. The skill stops and asks for them before it assesses anything. Section 6 has working defaults.
A9: 1. Scope of this workbook
A10: Key | B10: Field | C10: Your answer | D10: How to answer | E10: Example
A11: org.name | B11: Organization or business unit this workbook covers | D11: One workbook per program. Where a business unit runs its own AI program with different rules, give it its own copy. | E11: Northfield Health, corporate IT
A12: org.industry | B12: Industry | D12: Sets the regulatory context the skill reads AI evidence against. | E12: Healthcare delivery
A13: org.regulators | B13: Regulations and contracts that bear on your AI use | D13: Comma-separated. Write None if nothing applies. The skill cites these when a gap touches a regulated requirement. | E13: HIPAA, state privacy law, EU AI Act as a deployer
A14: org.frameworks | B14: Frameworks you report or certify against | D14: Pick from the eight columns on the Compliance Mapping tab: CSA AICM, EU AI Act, ISO/IEC 42001, MITRE ATLAS, NIST AI RMF, NIST AI 600-1, OWASP, SOC 2. Comma-separated. The Verification sheet of every record cites these and leaves the others out. | E14: SOC 2, NIST AI RMF, ISO/IEC 42001
A15: org.customer_commitments | B15: Customer contract commitments that bear on AI | D15: No AI training on client data, residency, notice windows, audit rights. Write None if nothing applies. What you owe your customers, you need from the tools that touch their data. | E15: No AI training on client data; US-only processing
A16: org.scope_boundary | B16: What this program covers | D16: Name the boundary so nobody assumes coverage that is not there. | E16: Every AI tool, feature and agent staff or systems use
A17: org.scope_notes | B17: What sits outside the boundary, and who accepted that | D17: Consumer AI on personal devices, AI features in SaaS the business buys on a card, research use. Say who signed. | E17: Consumer AI on personal devices is out. Accepted by the CIO, March 2026.
A18: org.ai_policy | B18: AI acceptable-use policy | D18: The policy every approval is checked against. | E18: Published
A19: org.ai_policy_location | B19: Where the policy lives | D19: A link or a document name. Write None if there is no policy yet. | E19: Policy portal, AI-AUP-001
A21: 2. Governance and routing
A22: Every row arrives with a starter value. Change what differs at your organization. The quick references on the Start Here, Tool Function Mapping and Tool Registry tabs read these cells, so there is one place to change each thing.
A23: Key | B23: Field | C23: Your answer | D23: How to answer | E23: Example
A24: gov.owner | B24: AI governance program owner (name or role) | D24: If there is none yet, say who is covering. | E24: Director of Security Governance
A25: gov.sponsor | B25: Executive sponsor | D25: The person who would chair a governance review. | E25: CISO
A26: gov.committee | B26: Standing AI governance committee or review board | D26: Yes only if it meets on a cadence and records decisions. | E26: Yes
A27: gov.committee_members | B27: What it is called and who sits on it | D27: Roles are enough. | E27: AI Review Board: CISO, CIO, Privacy, Legal, Data, Engineering
A28: gov.approve_low | B28: Who approves a Low-risk tool | C28: Security reviewer | D28: Standard approval. One person, usually the reviewer who ran the assessment. | E28: Security reviewer
A29: gov.approve_medium | B29: Who approves a Medium-risk tool | C29: Department lead with security review | E29: Department lead with security review
A30: gov.approve_high | B30: Who approves a High-risk tool | C30: AI governance committee | E30: AI governance committee
A31: gov.approve_severe | B31: Who approves a Severe-risk tool | C31: Exception only: CISO and the committee, with an executive sponsor | D31: Severe-risk tools are prohibited by default. An exception is time-bounded and tracked on the Exception Tracker tab. | E31: Exception only: CISO and the committee, with an executive sponsor
A32: gov.review_low | B32: How often a Low-risk tool is reviewed | C32: Yearly | E32: Yearly
A33: gov.review_medium | B33: How often a Medium-risk tool is reviewed | C33: Every six months | E33: Every six months
A34: gov.review_high | B34: How often a High-risk tool is reviewed | C34: Quarterly | E34: Quarterly
A35: gov.review_severe | B35: How often a Severe-risk tool is reviewed | C35: Monthly | E35: Monthly
A36: gov.accept_low | B36: Who accepts residual risk at Low and Medium | C36: The business owner of the use case | D36: Acceptance belongs to someone who owns both the value and the loss. The record names the role, never a reviewer. | E36: The business owner of the use case
A37: gov.accept_high | B37: Who accepts residual risk at High | C37: The business unit head | E37: The business unit head
A38: gov.accept_severe | B38: Who accepts residual risk at Severe | C38: A named executive, with the exception on record | E38: A named executive, with the exception on record
A39: gov.exception_approver | B39: Who approves exceptions to your own AI policy or standard | C39: CISO | D39: An exception is a recorded, temporary departure from your own policy, usually with compensating controls. A different role from the one that accepts risk. | E39: CISO
A40: gov.reviewer | B40: Who signs that an assessment is complete | D40: The security function confirming the work was done at the depth required. Separate from accepting risk. | E40: AI security lead
A41: gov.verifier | B41: Who verifies the guardrails after deployment | D41: The person or team that walks the Verification sheet once the tool is live, collects the evidence and marks Pass or Fail. | E41: Security engineering
A42: gov.human_check | B42: Who checks an AI-drafted record before it counts | D42: A named role. The check covers the evidence and the factor scores, not only the conclusion. | E42: Director of Security Governance
A43: gov.triage_by | B43: Who answers intake questions about a tool | C43: The requester | D43: The requester is the usual answer: the person asking for the tool, who knows how it will be used. For an internal build, the engineering owner answers the build questions. | E43: The requester
A44: gov.risk_appetite | B44: Documented AI risk appetite or tolerance statement | C44: None | D44: Where one exists, acceptances are judged against it. Most organizations have none, which makes every acceptance a judgment call. Write None. | E44: None
A45: gov.reclass_triggers | B45: Events that trigger a reassessment outside the cadence | C45: Vendor security incident; scope expansion; model version change; vendor acquisition; new connector or MCP server; regulatory change; user complaint or near miss | D45: Any of these starts a reassessment whatever the cadence says. Edit the list. | E45: The starter list
A46: gov.kill_switch | B46: Who can disable a tool or agent immediately, and how | C46: Security analyst on call, through the identity provider and the AI gateway | D46: The record names this on every High and Severe tool. If the honest answer is nobody, write that. | E46: Security analyst on call, through the identity provider and the AI gateway
A48: 3. Tools you already own
A49: Write the product names, or None. More than one tool can do guardrail duty: list every one that does, separated by commas. The skill uses your names in every record: the SIEM the logs go to, the vault the secrets live in, the DLP that covers the prompts. The seven family rows are the default for "Control that meets it" on a record; the Guardrail Checklist tab has an optional "Your control" column for naming the tool or mechanism per guardrail where the family row is too coarse. Where a family is None, the record says so and points at the AI Security Tool Landscape tab.
A50: Key | B50: Field | C50: Your answer | D50: How to answer | E50: Example
A51: tools.idp | B51: Identity provider or SSO | D51: Where users and, increasingly, agents get an identity. | E51: Microsoft Entra ID
A52: tools.pam | B52: Privileged access management | E52: CyberArk (Palo Alto Networks)
A53: tools.secrets | B53: Secrets vault | E53: HashiCorp Vault
A54: tools.siem | B54: SIEM | D54: Where AI tool logs are expected to land. | E54: Microsoft Sentinel
A55: tools.dlp | B55: DLP, CASB or SSE | D55: The control that sees prompts, uploads and personal accounts. | E55: Microsoft Purview, Zscaler
A56: tools.edr | B56: Endpoint protection | E56: CrowdStrike Falcon
A57: tools.gateway | B57: AI gateway or LLM proxy | D57: The one place to put rate limits, logging and model pinning. Write None if there is no gateway yet. | E57: None
A58: tools.ticketing | B58: Ticketing or intake tool | D58: Where a request and its dates live. | E58: ServiceNow
A59: tools.grc | B59: GRC platform | E59: None
A60: tools.evidence_store | B60: Where assessment records and evidence are filed | E60: SharePoint, one folder per tool
A61: tools.code | B61: Code repository and CI | D61: Matters for internal builds and coding agents. | E61: GitHub Enterprise with Actions
A62: tools.cloud | B62: Primary cloud or clouds | E62: Azure and AWS
A63: fam.posture | B63: AI Posture & Governance: your tools | D63: AI-SPM, inventory, governance platform. One or more, or None. | E63: Microsoft Defender for Cloud
A64: fam.runtime | B64: Runtime Protection & Guardrails: your tools | D64: Prompt injection and jailbreak defense, output filtering, content safety. One or more, or None. | E64: Azure AI Content Safety, Lakera (Check Point)
A65: fam.discovery | B65: Shadow AI & Usage Discovery: your tools | D65: Where unsanctioned AI use shows up. Often the CASB or SSE. One or more, or None. | E65: Zscaler
A66: fam.observability | B66: Observability & Evaluation: your tools | D66: LLM observability, evaluation, red-team tooling. One or more, or None. | E66: Datadog, Promptfoo
A67: fam.data | B67: Data Protection for AI: your tools | D67: DSPM or DLP tuned for AI flows. One or more, or None. | E67: Microsoft Purview, Cyera
A68: fam.nhi | B68: NHI & Agentic Access: your tools | D68: Agent identity, service account governance, secrets. One or more, or None. | E68: Entra Agent ID, CyberArk, HashiCorp Vault
A69: fam.supply | B69: AI Supply Chain: your tools | D69: Model scanning, AI-BOM, MCP registry. One or more, or None. | E69: Snyk
A71: 4. Program rules
A72: The positions every new tool is held to. Each assessment stands on its own; nothing here is a list of what was approved before.
A73: Key | B73: Field | C73: Your answer | D73: How to answer | E73: Example
A74: ai.mcp_policy | B74: MCP server policy | C74: Vendor-signed servers only | D74: Which MCP servers an agent may load. The function library treats community and custom servers as High and Severe until reviewed. | E74: Vendor-signed servers only
A75: ai.training_position | B75: Required position on training with your data | C75: No training on our data, in writing, at every plan | D75: The record rates a tool against this. | E75: No training on our data, in writing, at every plan
A76: ai.data_ceiling | B76: Highest data class allowed in an approved AI tool without an exception | C76: Confidential | D76: Four data classes, fixed across the workbook: Public (Low), Internal (Medium), Confidential (High), Restricted (Severe: PII, PHI, payment, export-controlled or other regulated data, and data about minors). A request above the ceiling is routed as Severe and needs an exception. | E76: Confidential
A77: ai.autonomy_ceiling | B77: Highest agent autonomy allowed without an exception | C77: Autonomous within an allowlist; a person approves Severe actions only | D77: The seventh risk factor. A request above the ceiling is routed as Severe. | E77: Autonomous within an allowlist; a person approves Severe actions only
A78: ai.build_gate | B78: What an internal build needs before production | C78: Threat model, an evaluation run against the use case, a red-team pass at High and Severe, and a Tool Registry entry | D78: The conditions every internal build carries. Edit to match your SDLC. | E78: The starter list
A80: 5. Rules for AI use on vendor documents
A81: Vendor reports often come with usage limits: an NDA, a named-person portal, a read-only viewer, or a clause that bars AI processing. These two rows tell the skill what it may read.
A82: Key | B82: Field | C82: Your answer | D82: How to answer | E82: Example
A83: docs.approved_tools | B83: AI tools approved for vendor documents | D83: Name the tenant or product where vendor reports may be processed. | E83: Enterprise tenant only, no consumer tools
A84: docs.restricted_default | B84: What happens when a vendor document carries usage limits | C84: Keep on a manual review path | D84: The manual path is the cautious choice: a person reads the document and passes back a short checklist. | E84: Keep on a manual review path
A86: 6. Your records
A87: How assessment records look and read. Every row has a working default, so change only what you want changed.
A88: Key | B88: Field | C88: Your answer | D88: How to answer | E88: Example
A89: out.term | B89: What you call the thing assessed | C89: AI tool | D89: AI tool, AI system, use case or application. Used in the record labels. | E89: AI tool
A90: out.format | B90: Record format | C90: Excel record | D90: The Excel record is built by a script and looks the same every time. The other two carry the same sections. | E90: Excel record
A91: out.file_pattern | B91: File name pattern | C91: AI_Risk_Assessment_<Tool>_<YYYY-MM-DD>.xlsx | D91: The tool name is written in letters, digits and underscores only. | E91: AI_Risk_Assessment_<Tool>_<YYYY-MM-DD>.xlsx
A92: out.id_pattern | B92: Record ID pattern | C92: AIR-<YYYY>-<TOOL> | D92: A second pass on the same tool keeps the ID and takes a new date. | E92: AIR-<YYYY>-<TOOL>
A93: out.title_color | B93: Title bar color | C93: 1F3864 | D93: Six-character hex code. | E93: 1F3864
A94: out.section_color | B94: Section header color | C94: 305496 | D94: Six-character hex code. | E94: 305496
A95: out.header_color | B95: Table header color | C95: D9E1F2 | D95: Six-character hex code. | E95: D9E1F2
A96: out.font | B96: Font | C96: Arial | E96: Arial
A97: out.footer | B97: Footer line on every record | C97: None | D97: For example: Internal use. Vendor evidence may be covered by an NDA. Write None for no footer. | E97: None
A98: out.added_steps | B98: Steps your process adds to every assessment | C98: None | D98: For example: privacy review for any tool holding Restricted data, legal review before signature. They appear as conditions on every record. | E98: None
A99: out.question_cap | B99: Most questions sent to the vendor or the requester on one record | C99: 4 | D99: A question is drafted only where an answer would move a risk factor up or down. Zero questions is a valid record. | E99: 4

Sheet Tool Function Mapping
A1: AI Security Risk Workbook: Tool Function Mapping
A3: Classify a tool by the seven risk factors, then list every function it performs. Each function rolls up to a risk level, the agentic flag, the guardrails it requires and the families those guardrails live in. The skill reads both tables by the keys in column A.
A5: Cream cells | B5: The factor wording, the function rows and the three blank rows at the bottom are yours to change or add to.
A6: Rose cells | B6: Keys the skill reads, and the routing quick reference calculated from Org Profile.
A8: 1. Risk classification criteria
A9: Score each factor. The highest-rated factor sets the overall risk level. Agent autonomy drives the agentic flag: anything above "no autonomy" picks up every agentic guardrail whatever the level. Reword a level to fit your environment; keep the four names.
A10: table:risk.factors | B10: Risk factor | C10: Low | D10: Medium | E10: High | G10: Severe
A11: risk.factors | B11: Data sensitivity | C11: Public: information anyone may see | D11: Internal: company information that is not sensitive | E11: Confidential: trade secrets, IP, internal strategy, customer business data | G11: Restricted: PII, PHI, payment, export-controlled or other regulated data; data about minors
A12: risk.factors | B12: Access permissions | C12: Read-only, scoped | D12: Limited write to scoped resources | E12: Full read and write on production resources | G12: Admin, root or infrastructure control
A13: risk.factors | B13: Integration depth | C13: Isolated, no integrations | D13: Limited API, rate-capped | E13: Direct system access: database, filesystem, connectors | G13: Privileged control plane: IAM, secrets, infrastructure
A14: risk.factors | B14: Action reversibility | C14: Read-only, no state change | D14: Reversible writes: edit a document, retry a task | E14: Hard to reverse: send an email, trigger a payment | G14: Irreversible: delete records, post publicly, move money
A15: risk.factors | B15: Data persistence | C15: None, ephemeral | D15: Session only, cleared on close | E15: Cached or stored, TTL-bounded, user-owned | G15: Vendor retains and may train; memory shared across users
A16: risk.factors | B16: External access | C16: None, internal only | D16: Allowlisted endpoints, logged | E16: Broad internet with logged egress | G16: Unrestricted or unlogged egress
A17: risk.factors | B17: Agent autonomy | C17: No autonomy: a person prompts each action | D17: Scoped autonomy with a person approving every write | E17: Autonomous within an allowlist; a person approves Severe actions only | G17: Fully autonomous, no human gate, may spawn sub-agents
A18: Scoring rule: the highest rating across any factor sets the overall risk level. A tool whose agent autonomy sits above the Org Profile ceiling is routed as Severe.
A20: 2. Routing quick reference
A21: Calculated from Org Profile section 2. Change it there.
A22: Risk level | B22: Approved by | E22: Reviewed | G22: Residual risk accepted by
A23: Low | B23: ='Org Profile'!C28 -> Security reviewer | E23: ='Org Profile'!C32 -> Yearly | G23: ='Org Profile'!C36 -> The business owner of the use case
A24: Medium | B24: ='Org Profile'!C29 -> Department lead with security review | E24: ='Org Profile'!C33 -> Every six months | G24: ='Org Profile'!C36 -> The business owner of the use case
A25: High | B25: ='Org Profile'!C30 -> AI governance committee | E25: ='Org Profile'!C34 -> Quarterly | G25: ='Org Profile'!C37 -> The business unit head
A26: Severe | B26: ='Org Profile'!C31 -> Exception only: CISO and the committee, with an executive sponsor | E26: ='Org Profile'!C35 -> Monthly | G26: ='Org Profile'!C38 -> A named executive, with the exception on record
A28: 3. Function to guardrails to families
A29: Identify every function the tool performs; the union of their guardrails, plus the Every tool and Vendor products rows on the Guardrail Checklist, is the tool's required list. Nearly every tool performs the two text functions (LLM prompt processing and AI response generation), which carry the controls any model-backed tool needs; the other functions carry what is specific to them. "Required guardrails" is what a person reads and "Guardrail IDs" is what the skill reads; both come from the Guardrail Checklist, so edit the IDs and the names follow. "Example products" come from the AI Security Tool Landscape; in your own records the skill names the tool you own for each family from Org Profile section 3. Set Active to Off to drop a function, and add your own in the blank rows.
A30: table:functions | B30: Function | C30: Risk | D30: Agentic? | E30: Required guardrails | F30: Guardrail IDs | G30: Families | H30: Example products | I30: Active
A31: functions | B31: Time, date and timezone calculations | C31: Low | D31: No | E31: audit logging | F31: OBS-01 | G31: Observability | I31: On
A32: functions | B32: Public data lookups (weather, rates, reference APIs) | C32: Low | D32: No | E32: rate limiting (per user); domain restrictions (egress); audit logging | F32: RUN-03; RUN-07; OBS-01 | G32: Runtime, Observability | I32: On
A33: functions | B33: Geographic and mapping information | C33: Low | D33: No | E33: pII detection; domain restrictions (egress); audit logging | F33: DAT-02; RUN-07; OBS-01 | G33: Data Protection, Runtime, Observability | I33: On
A34: functions | B34: Basic system health checks (read-only) | C34: Low | D34: No | E34: service account scoping; secrets management; audit logging | F34: NHI-01; NHI-02; OBS-01 | G34: NHI, Observability | H34: Datadog, Arize | I34: On
A35: functions | B35: Static file read (public or non-sensitive) | C35: Low | D35: No | E35: service account scoping; data classification; audit logging | F35: NHI-01; DAT-03; OBS-01 | G35: NHI, Data Protection, Observability | I35: On
A36: functions | B36: Online search interfaces | C36: Medium | D36: No | E36: rate limiting (per user); domain restrictions (egress); dLP rules active; audit logging | F36: RUN-03; RUN-07; DAT-01; OBS-01 | G36: Runtime, Data Protection, Observability | H36: Harmonic, Nightfall, Netskope | I36: On
A37: functions | B37: Web data extraction and scraping | C37: Medium | D37: No | E37: domain restrictions (egress); input validation; audit logging; red team and adversarial testing | F37: RUN-07; RUN-01; OBS-01; OBS-06 | G37: Runtime, Observability | H37: Netskope, Zscaler, Island | I37: On
A38: functions | B38: Automated task execution (scoped) | C38: Medium | D38: Yes | E38: agent authentication; intent validation; tool and function authorization; secrets management; short-lived tokens; rate limiting (per workload); alerting configured; agent behavior monitoring; red team and adversarial testing | F38: NHI-05; NHI-06; NHI-07; NHI-02; NHI-04; RUN-04; OBS-04; OBS-08; OBS-06 | G38: NHI, Runtime, Observability | H38: Arthur, Mindgard, Datadog | I38: On
A39: functions | B39: Log processing and event analysis | C39: Medium | D39: No | E39: service account scoping; pII detection; data masking; data classification; audit logging | F39: NHI-01; DAT-02; DAT-06; DAT-03; OBS-01 | G39: NHI, Data Protection, Observability | H39: Datadog, Arize, Splunk | I39: On
A40: functions | B40: Enterprise data queries (read-only) | C40: Medium | D40: No | E40: service account scoping; secrets management; credential rotation; dLP rules active; pII detection; data classification; audit logging; sIEM integration; alerting configured | F40: NHI-01; NHI-02; NHI-03; DAT-01; DAT-02; DAT-03; OBS-01; OBS-03; OBS-04 | G40: NHI, Data Protection, Observability | H40: Cyera, BigID, Knostic | I40: On
A41: functions | B41: Internal documentation retrieval | C41: Medium | D41: No | E41: service account scoping; secrets management; credential rotation; dLP rules active; data classification; audit logging; sIEM integration; alerting configured; vector store security | F41: NHI-01; NHI-02; NHI-03; DAT-01; DAT-03; OBS-01; OBS-03; OBS-04; SUP-10 | G41: NHI, Data Protection, Observability, Supply Chain | H41: Knostic, Cyera, Reco | I41: On
A42: functions | B42: Code repository read access | C42: Medium | D42: No | E42: service account scoping; secrets management; credential rotation; data classification; audit logging | F42: NHI-01; NHI-02; NHI-03; DAT-03; OBS-01 | G42: NHI, Data Protection, Observability | H42: Wiz, Noma, GitGuardian | I42: On
A43: functions | B43: Email, chat and messaging read access | C43: Medium | D43: No | E43: service account scoping; secrets management; credential rotation; dLP rules active; pII detection; data classification; audit logging; sIEM integration; alerting configured | F43: NHI-01; NHI-02; NHI-03; DAT-01; DAT-02; DAT-03; OBS-01; OBS-03; OBS-04 | G43: NHI, Data Protection, Observability | H43: Harmonic, Nightfall, Knostic | I43: On
A44: functions | B44: LLM prompt processing (text) | C44: Medium | D44: No | E44: input validation; rate limiting (per user); content safety; fallback and graceful degradation; audit logging; log retention; user access tracked; usage analytics; model provenance; model version pinning; model rollback procedure; third-party model assessment; system prompt protection; encryption in transit; encryption at rest; retention policies; training data opt-out; incident disclosure to users; data residency review | F44: RUN-01; RUN-03; RUN-05; RUN-09; OBS-01; OBS-02; SHA-03; SHA-04; SUP-01; SUP-02; SUP-03; SUP-08; SUP-11; DAT-04; DAT-05; DAT-07; DAT-08; DAT-10; POS-08 | G44: Runtime, Observability, Shadow AI, Supply Chain, Data Protection, Posture | H44: Arthur, Mindgard, Prompt Armor, Lakera (Check Point) | I44: On
A45: functions | B45: Multi-modal input processing (image, audio, video) | C45: Medium | D45: No | E45: multi-modal input validation; content safety; input validation | F45: RUN-06; RUN-05; RUN-01 | G45: Runtime | H45: Lakera (Check Point), Azure AI Content Safety, Google Model Armor | I45: On
A46: functions | B46: AI response generation (text) | C46: Medium | D46: No | E46: output filtering; content safety; performance and drift monitoring; audit logging | F46: RUN-02; RUN-05; OBS-05; OBS-01 | G46: Runtime, Observability | H46: Arthur, Patronus, Arize | I46: On
A47: functions | B47: Vector database queries (read-only) | C47: Medium | D47: No | E47: vector store security; embedding integrity; service account scoping; pII detection; audit logging | F47: SUP-10; SUP-12; NHI-01; DAT-02; OBS-01 | G47: Supply Chain, NHI, Data Protection, Observability | H47: Knostic, Cyera, Wiz | I47: On
... A87: functions | B87: Dynamic model swap at runtime | C87: Severe | D87: Yes | E87: model provenance; model version pinning; model rollback procedure; model integrity verification; performance and drift monitoring | F87: SUP-01; SUP-02; SUP-03; SUP-07; OBS-05 | G87: Supply Chain, Observability | H87: Model registry with attestation | I87: On
A88: functions
A89: functions
A90: functions
A91: 57 functions, 30 flagged agentic. Low: standard approval. Medium: department lead with security review. High: committee review. Severe: exception required. Those are the starter routes; Org Profile section 2 holds yours.

Sheet Guardrail Checklist
A1: AI Security Risk Workbook: Guardrail Checklist
A3: The control library. A guardrail is required for a tool only when a function the tool performs lists it on the Tool Function Mapping tab, so the record for a drafting assistant and the record for an agent that runs shell commands carry different lists. In scope says which rule applies: Every tool = the program's own steps (register, classify, approve, assign an owner), required whatever the tool does | Vendor products = required for anything bought | By function = required only when a listed function names it; the next column shows which functions do. The risk level routes the decision and sets who approves; it does not add guardrails. The agentic flag marks which guardrails are agent controls; it does not put them in scope either. At issue, the record lists every required guardrail with its owner and the control that meets it. After deployment, the Verification sheet in the record file carries the same rows with their verification criteria and evidence, for a person to mark Pass or Fail.
A5: Cream cells | B5: The wording, In scope, the Agentic flag, Your control and Active are yours. Set Active to Off to drop a guardrail from every record without deleting the row; add your own in the blank rows with the family name spelled as it is here. "Required by functions" is calculated from the Tool Function Mapping tab when the workbook is built.
A6: Rose cells | B6: Keys the skill reads. The ID column is the join to the Tool Function Mapping and Compliance Mapping tabs, so keep IDs stable.
A8: 1. The seven families
A9: Family | C9: What it covers | H9: In one line
A10: AI Posture & Governance (POS) | C10: Inventory, risk classification, approval, policy, vendor and compliance review | H10: What AI is in use, who owns it, whether it was approved and against which rules
A11: Runtime Protection & Guardrails (RUN) | C11: Prompt injection and jailbreak defense, output filtering, content safety, rate and cost limits, egress control | H11: The controls that sit in the request path while the tool runs
A12: Shadow AI & Usage Discovery (SHA) | C12: Finding AI use you did not sanction, tracking who uses what, blocking personal accounts | H12: You cannot govern what you cannot see
A13: Observability & Evaluation (OBS) | C13: Audit logging, retention, SIEM, alerting, drift and hallucination monitoring, red teaming, bias testing, agent behavior monitoring | H13: The evidence that the controls work, and the early warning when they stop working
A14: Data Protection for AI (DAT) | C14: DLP, PII detection, classification, encryption, masking, retention, training opt-out, provenance marking, user disclosure | H14: What data reaches the model, what the model keeps, and what leaves
A15: NHI & Agentic Access (NHI) | C15: Service accounts, secrets, rotation, short-lived tokens, agent identity, intent and tool authorization, spawn limits, autonomy limits, boundaries, sandboxes, memory | H15: Identity is the control plane for agents: what an agent is, what it may call, and how far it may go
A16: AI Supply Chain (SUP) | C16: Model provenance, pinning, rollback, training data lineage and consent, pipeline security, integrity checks, third-party models, plugins and MCP servers, vector stores, system prompts, embeddings, action attestation | H16: Where the model, its data, its tools and its prompts came from, and whether they are still what you reviewed
A18: 2. Guardrails
A19: "Your control" is optional: the tool or mechanism that meets this guardrail at your organization where the family tools on Org Profile section 3 are too coarse, for example HashiCorp Vault on NHI-02 when the NHI family row lists three tools, Microsoft Purview on DAT-02, the Tool Registry tab on POS-01, the AI governance committee on POS-03, or a contract clause on DAT-08. Separate several with commas. Blank means the family tools; the record fills "Control that meets it" from here first, then from the family row. "Active" is the switch: Off drops the guardrail from every record without deleting it.
A20: table:guardrails | B20: ID | C20: Family | D20: Guardrail | E20: In scope | F20: Agentic? | G20: Required by functions | H20: Verification criteria | I20: Evidence artifact | J20: Your control | K20: Active
A21: guardrails | B21: POS-01 | C21: AI Posture & Governance | D21: Tool registration | E21: Every tool | F21: No | G21: Every tool, whatever its functions | H21: The tool has an entry in the Tool Registry with every required field filled in. | I21: Tool Registry row: tool, vendor or builder, source, risk level, owners, status. Exported or linked. | K21: On
A22: guardrails | B22: POS-02 | C22: AI Posture & Governance | D22: Risk classification | E22: Every tool | F22: No | G22: Every tool, whatever its functions | H22: The seven risk factors are scored and the highest factor sets the level. The functions the tool performs are listed. | I22: The assessment record, section 4, with the factor scores and the function list. | K22: On
A23: guardrails | B23: POS-03 | C23: AI Posture & Governance | D23: Approval obtained | E23: Every tool | F23: No | G23: Every tool, whatever its functions | H23: Approval is recorded at the level the Org Profile sets for this risk level, with conditions written down. | I23: Ticket or workflow record of the approval, linked from the Tool Registry. | K23: On
A24: guardrails | B24: POS-04 | C24: AI Posture & Governance | D24: Policy alignment | E24: Every tool | F24: No | G24: Every tool, whatever its functions | H24: The use fits the AI acceptable-use policy and any data handling rules it points to. | I24: Signed acknowledgment from the tool owner, or the policy clause the use falls under. | K24: On
A25: guardrails | B25: POS-05 | C25: AI Posture & Governance | D25: Owner assignment | E25: Every tool | F25: No | G25: Every tool, whatever its functions | H25: A business owner and a technical owner are named, and both know they own it. | I25: Tool Registry: Business Owner and Technical Owner fields filled in. | K25: On
A26: guardrails | B26: POS-06 | C26: AI Posture & Governance | D26: Vendor assessment | E26: Vendor products | F26: No | G26: Every vendor product and vendor-added AI feature | H26: The vendor's security posture has been assessed: a SOC 2 Type II or ISO 27001 certificate reviewed, the DPA read, the AI data-handling terms confirmed. | I26: Vendor risk record: SOC 2 Type II under 12 months old, DPA, AI addendum or equivalent, filed in the evidence store. | K26: On
A27: guardrails | B27: POS-07 | C27: AI Posture & Governance | D27: Compliance mapping | E27: By function | F27: No | G27: 5 functions: HR, financial or PII system access; Model-in-the-loop decision routing; Log analysis containing PII or regulated data; Model fine-tuning with production data; Autonomous decision-making on consequential actions | H27: The tool is mapped to the frameworks the organization answers to, using the Compliance Mapping tab. | I27: Completed framework mapping for this tool, stored in the GRC tool or the evidence store. | K27: On
A28: guardrails | B28: POS-08 | C28: AI Posture & Governance | D28: Data residency review | E28: By function | F28: No | G28: 4 functions: LLM prompt processing (text); Enterprise file indexing and search; RAG with confidential documents; Log analysis containing PII or regulated data | H28: Where prompts, outputs, embeddings and logs are processed and stored is known and fits the residency requirements. | I28: Vendor DPA or architecture note naming the regions, checked against the requirements. | K28: On
A29: guardrails | B29: RUN-01 | C29: Runtime Protection & Guardrails | D29: Input validation | E29: By function | F29: No | G29: 5 functions: Web data extraction and scraping; LLM prompt processing (text); Multi-modal input processing (image, audio, video); RAG with confidential documents; Autonomous web browsing | H29: Prompt injection detection runs on every user-supplied input and on retrieved content before it reaches the model. | I29: Runtime product or gateway configuration showing detection enabled, plus a sample blocked request. | K29: On
A30: guardrails | B30: RUN-02 | C30: Runtime Protection & Guardrails | D30: Output filtering | E30: By function | F30: No | G30: 3 functions: AI response generation (text); Automated messaging and email send; Content generation for external publication | H30: Model outputs pass through content filtering and PII redaction before a person or a downstream system sees them. | I30: Filter rules and a sample blocked or redacted response from the log. | K30: On
A31: guardrails | B31: RUN-03 | C31: Runtime Protection & Guardrails | D31: Rate limiting (per user) | E31: By function | F31: No | G31: 3 functions: Public data lookups (weather, rates, reference APIs); Online search interfaces; LLM prompt processing (text) | H31: Per-user request and token limits are configured and enforced. | I31: API gateway or product configuration with the limit values. | K31: On
A32: guardrails | B32: RUN-04 | C32: Runtime Protection & Guardrails | D32: Rate limiting (per workload) | E32: By function | F32: Yes | G32: 9 functions: Automated task execution (scoped); Prompt chaining and workflow orchestration; MCP server: vendor-signed or verified; Code execution in an ephemeral sandbox; Tool and function calling by AI agents; Sub-agent spawning (bounded); Long-running or background agents; Multi-agent orchestration (autonomous); Agent task delegation or unbounded spawning | H32: Per-workload and per-agent request, token and cost ceilings stop a runaway task. | I32: Gateway quota configuration and the cost alert rule. | K32: On
... A85: guardrails | B85: SUP-13 | C85: AI Supply Chain | D85: Agent action attestation | E85: By function | F85: Yes | G85: 9 functions: Human-in-the-loop approval workflows; Sub-agent spawning (bounded); Privileged system automation (production infrastructure); Unrestricted code execution (no sandbox); Infrastructure automation (Terraform, Kubernetes); Autonomous agent with unrestricted API access; Multi-agent orchestration (autonomous); Agent task delegation or unbounded spawning; Autonomous decision-making on consequential actions | H85: Critical agent actions are signed and attested, so an action can be tied to the agent, the person and the inputs that produced it. | I85: Signed action log and the verification procedure. | K85: On
A86: guardrails
A87: guardrails
A88: guardrails
A89: 65 guardrails: 7 for every tool, 2 for vendor products, 56 by function. 21 flagged agentic. New in v3.0: OBS-08 Agent behavior monitoring and NHI-12 Agent memory protection.

Sheet Intake Form
A1: AI Security Risk Workbook: Intake Form
A3: One form per request, about five minutes. Only the tool name and the kind of request are required. Pick from the list wherever a row has one; Not sure is always an acceptable answer, and the skill fills what public pages can answer. A vendor product gets researched from what the vendor publishes. Something you built has no public pages, so section 4 is where its assessment comes from. Copy this tab per request, or use the standalone AI_Intake_Form.xlsx.
A5: Cream cells | B5: Yours to fill in.
A6: Rose cells | B6: Do not edit. Column A holds the keys the skill reads.
A8: 1. The request
A9: Only the first two rows are required. Pick from the list wherever a row has one; Not sure is always an acceptable answer.
A10: Key | B10: Field | C10: Your answer | D10: How to answer
A11: intake.tool | B11: Tool, product or use case name | D11: Required.
A12: intake.source | B12: Which kind of request this is | D12: Required. It decides how the assessment runs: a vendor product is researched from what the vendor publishes, and an internal build is uncovered from section 4 because nothing about it is public.
A13: intake.vendor | B13: Vendor or builder | D13: The company. For an internal build, write Internal and the team.
A14: intake.website | B14: Website or internal location | D14: Helps the skill find the right company or repository.
A15: intake.requester | B15: Your name and role
A16: intake.business_owner | B16: Business owner of the use case | D16: The person who would decide whether a risk is worth taking.
A17: intake.stage | B17: Where this stands
A18: intake.requested_on | B18: Date of this request | D18: Lets the program measure the time from request to decision.
A20: 2. How it will be used
A21: These map to the seven risk factors.
A22: Key | B22: Field | C22: Your answer | D22: How to answer
A23: intake.purpose | B23: What it will do for you | D23: A sentence is enough.
A24: intake.users | B24: Roughly how many people will use it
A25: intake.exposure | B25: Who can reach it
A26: intake.data_class | B26: Highest data class it will see or hold | D26: Four data classes, fixed across the workbook: Public (Low), Internal (Medium), Confidential (High), Restricted (Severe: PII, PHI, payment, export-controlled or other regulated data, and data about minors).
A27: intake.data_examples | B27: Name the kinds of data | D27: Contracts, tickets, source code, patient notes. A few words.
A28: intake.regulated | B28: Is any of it in scope for a regulator or a customer contract | D28: HIPAA, PCI DSS, a state privacy law, a client security addendum, the EU AI Act.
A29: intake.connects | B29: How it connects to your systems | D29: Pick the deepest one that applies.
A30: intake.actions | B30: What it can do on its own | D30: The agent autonomy factor.
A31: intake.tool_calling | B31: Calls tools, functions or APIs on its own
A32: intake.subagents | B32: Spawns sub-agents or delegates tasks to other agents
A33: intake.long_running | B33: Runs long or in the background without a person watching
A34: intake.computer_use | B34: Controls a screen, mouse or keyboard
A35: intake.memory | B35: Keeps memory or context between sessions
A36: intake.mcp | B36: MCP servers, plugins or extensions it loads
A37: intake.external | B37: Browses the web or calls outside services
A38: intake.training | B38: Is your data used to train or improve models
A40: 3. Vendor products only
A41: Skip for an internal build. For an existing vendor adding AI, answer what you can and fill the last two rows.
A42: Key | B42: Field | C42: Your answer | D42: How to answer
A43: intake.plan | B43: Plan, tier or edition | D43: Controls such as SSO, audit export, data residency and the training opt-out often depend on the plan.
A44: intake.deployment | B44: How it runs
A45: intake.region | B45: Where our data is processed
A46: intake.trust_center | B46: Trust center or security page address | D46: If you know it.
A47: intake.doc_iso42001 | B47: ISO/IEC 42001 certificate | D47: The AI management system standard. The strongest single piece of vendor-side evidence; look for it first.
A48: intake.doc_soc2 | B48: SOC 2 report | D48: Usually behind a request button or an NDA on the trust center.
A49: intake.doc_dpa | B49: Data processing agreement, AI addendum or AI terms | D49: The document that says what happens to your prompts and data.
A50: intake.doc_limits | B50: Do any of those documents carry limits on use | D50: An NDA, access for one named person, a clause that bars AI processing.
A51: intake.ai_feature_default | B51: For an existing vendor: how the new AI feature arrived
A52: intake.ai_feature | B52: For an existing vendor: what the new AI feature does | D52: A sentence.
A54: 4. Internal builds only
A55: There are no public pages for something you built, so this section is where the assessment comes from. The engineering owner usually answers it in ten minutes.
A56: Key | B56: Field | C56: Your answer | D56: How to answer
A57: intake.model_access | B57: How the model is reached
A58: intake.model | B58: Which model and provider | D58: GPT-5 through Azure OpenAI; Claude through Bedrock; Llama self-hosted.
A59: intake.hosting | B59: Where it runs
A60: intake.data_sources | B60: What it reads | D60: Systems, repositories, indexes, vector stores, document libraries.
A61: intake.tools | B61: What tools or actions it can call, and with whose credentials | D61: Each tool, what it does, and the identity it uses. Write None if it only answers.
A62: intake.identity | B62: How it authenticates to those systems
A63: intake.logging | B63: What is logged
A64: intake.log_destination | B64: Where the logs go
A65: intake.testing | B65: Testing done so far
A66: intake.eng_owner | B66: Engineering owner | D66: Who answers for the build.
A67: intake.go_live | B67: Planned go-live, or the date it went live

Sheet Tool Registry
A1: AI Security Risk Workbook: Tool Registry
A3: Living inventory of every AI tool, vendor AI feature and internal build. Customize the columns for your organization (budget codes, contract dates, agent counts). Never delete a row: set Status to Decommissioned so the audit trail survives. The sample rows show the shape; replace them with yours.
A6: 1. Quick reference
A7: Read from Org Profile section 2. Change it there.
A8: Risk level | B8: Approved by | E8: Reviewed | G8: Residual risk accepted by
A9: Low | B9: ='Org Profile'!C28 -> Security reviewer | E9: ='Org Profile'!C32 -> Yearly | G9: ='Org Profile'!C36 -> The business owner of the use case
A10: Medium | B10: ='Org Profile'!C29 -> Department lead with security review | E10: ='Org Profile'!C33 -> Every six months | G10: ='Org Profile'!C36 -> The business owner of the use case
A11: High | B11: ='Org Profile'!C30 -> AI governance committee | E11: ='Org Profile'!C34 -> Quarterly | G11: ='Org Profile'!C37 -> The business unit head
A12: Severe | B12: ='Org Profile'!C31 -> Exception only: CISO and the committee, with an executive sponsor | E12: ='Org Profile'!C35 -> Monthly | G12: ='Org Profile'!C38 -> A named executive, with the exception on record
A13: Status legend: Active | Under review | Suspended | Exception | Decommissioned. Source: Vendor product | Vendor-added AI | Internal build.
A15: 2. Tool inventory
A16: Record ID | B16: Tool name | C16: Vendor or builder | D16: Source | E16: Risk | F16: Agentic? | G16: Data class | H16: Functions | I16: Required families | J16: Guardrail status | K16: Business owner | L16: Technical owner | M16: Approved | N16: Last review | O16: Next review | P16: Status | Q16: Exception # | R16: Model or provider | S16: Cost center | T16: Contract expiry | U16: Data residency | V16: Regulatory scope | W16: Annual spend | X16: Notes
A17: AIR-2026-CHATGPT | B17: ChatGPT Enterprise | C17: OpenAI | D17: Vendor product | E17: Medium | F17: No | G17: Internal | H17: Content generation, Q&A | I17: Posture, Runtime, Shadow AI, Observability | J17: In scope: 21 of 21 passed | K17: Marketing | L17: IT Security | M17: 2026-01-15 | N17: 2026-07-15 | O17: 2027-01-15 | P17: Active | R17: OpenAI GPT-5 | S17: MKT-100 | T17: 2027-01-14 | U17: US | V17: SOC 2, ISO 27001 | W17: $100K | X17: SSO through Entra; training opt-out in the agreement
A18: AIR-2026-COPILOT | B18: GitHub Copilot Enterprise | C18: Microsoft | D18: Vendor product | E18: Medium | F18: Yes | G18: Confidential | H18: Code generation, code review, coding agent | I18: Posture, Runtime, Data Protection, NHI, Supply Chain | J18: In scope: 33 of 35 passed; NHI-04 and SUP-09 open | K18: Engineering | L18: DevSecOps | M18: 2025-10-01 | N18: 2026-07-15 | O18: 2027-01-15 | P18: Active | R18: OpenAI and Anthropic models through GitHub | S18: ENG-200 | T18: 2026-09-30 | U18: US and EU | V18: SOC 2 | W18: $480K | X18: Content exclusions configured; coding agent limited to pull requests
A19: AIR-2026-CLAUDE | B19: Claude Enterprise | C19: Anthropic | D19: Vendor product | E19: Medium | F19: Yes | G19: Confidential | H19: Content generation, RAG, MCP connectors | I19: Posture, Runtime, Data Protection, NHI, Supply Chain | J19: In scope: 35 of 35 passed | K19: Research | L19: IT Security | M19: 2026-01-20 | N19: 2026-09-15 | O19: 2027-03-15 | P19: Active | R19: Anthropic Claude | S19: R&D-300 | T19: 2027-01-19 | U19: US and EU | V19: SOC 2 | W19: $220K | X19: MCP connector allowlist; memory off for regulated users
A20: AIR-2026-BEDROCK | B20: AWS Bedrock (Claude, Llama) | C20: AWS | D20: Vendor product | E20: High | F20: Yes | G20: Restricted | H20: LLM through API, Bedrock Agents, RAG | I20: All seven families | J20: In scope: 51 of 54 passed; 3 open | K20: Platform Engineering | L20: Cloud Security | M20: 2026-02-10 | N20: 2026-08-10 | O20: 2026-11-10 | P20: Active | R20: Anthropic Claude, Meta Llama through Bedrock | S20: PLAT-400 | T20: Platform | U20: US | V20: SOC 2, ISO 27001, HIPAA-eligible | W20: $1.2M | X20: VPC endpoints only; CloudTrail to the SIEM; customer-managed keys
A21: AIR-2026-CLAIMS | B21: Claims summarization assistant | C21: Internal (Data Science) | D21: Internal build | E21: High | F21: No | G21: Restricted | H21: RAG with confidential documents, AI response generation | I21: Posture, Runtime, Observability, Data Protection, Supply Chain | J21: In scope: 44 of 48 passed; red team scheduled | K21: Claims Operations | L21: ML Platform | M21: 2026-09-01 | N21: 2026-09-01 | O21: 2026-12-01 | P21: Active | R21: Azure OpenAI GPT-5 | S21: DS-500 | T21: Internal | U21: US | V21: HIPAA, SOC 2 | W21: $850K | X21: Vector store need-to-know enforced; evaluation set on file
A22: AIR-2026-OPSAGENT | B22: Operations agent (pilot) | C22: Vendor X | D22: Vendor product | E22: Severe | F22: Yes | G22: Confidential | H22: Task automation, external API calls, RAG | I22: All seven families | J22: In scope: 63 of 65 passed; HITL on every external action | K22: Operations | L22: Security | M22: 2026-06-01 | N22: 2026-09-01 | O22: 2026-10-01 | P22: Exception | Q22: EXC-2026-001 | R22: Vendor-hosted, OpenAI models | S22: OPS-600 | T22: 2026-12-01 | U22: US | V22: SOC 2 | W22: $400K | X22: Monthly review; kill switch tested quarterly
A23: AIR-2026-SLACKMCP | B23: Slack MCP server | C23: Anthropic registry | D23: Vendor product | E23: High | F23: Yes | G23: Internal | H23: Agent tool for Slack read and write | I23: Runtime, NHI, Supply Chain | J23: In scope: 40 of 42 passed | K23: IT Operations | L23: Security Engineering | M23: 2026-03-10 | N23: 2026-09-10 | O23: 2026-12-10 | P23: Active | R23: Not applicable | S23: IT-700 | T23: Not applicable | U23: US | V23: SOC 2 | W23: $0 | X23: Vendor-signed server; scoped to approved channels; per-call authorization
A24: AIR-2026-SFDC-AI | B24: Salesforce Agentforce (added AI feature) | C24: Salesforce | D24: Vendor-added AI | E24: High | F24: Yes | G24: Confidential | H24: Tool calling by AI agents, automated messaging | I24: Posture, Runtime, Data Protection, NHI | J24: In scope: 38 of 44 passed; 6 open | K24: Sales Operations | L24: CRM Platform | M24: 2026-08-20 | N24: 2026-08-20 | O24: 2026-11-20 | P24: Under review | R24: Salesforce Einstein Trust Layer | S24: SALES-250 | T24: 2027-06-30 | U24: US | V24: SOC 2 | W24: Included | X24: Feature was on by default; agent actions limited to drafts pending the open guardrails
A25: AIR-2026-PINECONE | B25: Pinecone (RAG vector store) | C25: Pinecone | D25: Vendor product | E25: High | F25: No | G25: Confidential | H25: Vector database queries, vector database write | I25: Data Protection, Posture, NHI, Supply Chain | J25: In scope: 46 of 48 passed | K25: Data Platform | L25: Cloud Security | M25: 2025-12-15 | N25: 2026-08-20 | O25: 2026-11-20 | P25: Active | R25: Not applicable | S25: DATA-800 | T25: 2026-12-14 | U25: US | V25: SOC 2 | W25: $180K | X25: Private Link; customer-managed keys; no PII in embeddings
A26: AIR-2025-SUPPORTBOT | B26: Legacy support chatbot | C26: Vendor Y | D26: Vendor product | E26: Medium | F26: No | G26: Internal | H26: Q&A on internal documents | I26: Posture, Runtime, Observability | J26: DAT-01 failed at review | K26: Support | L26: IT Operations | M26: 2025-06-01 | N26: 2026-06-01 | O26: 2026-12-01 | P26: Suspended | R26: Vendor-hosted, undisclosed | S26: SUP-900 | T26: 2026-05-31 | U26: US | W26: $24K | X26: DLP rule failed the audit; remediation in progress

Sheet Exception Tracker
A1: AI Security Risk Workbook: Exception Tracker
A3: Track exceptions for Severe-risk tools, guardrail deviations, vendor gaps, compliance gaps, emergency use, model versions and pilots. An exception is a recorded, temporary departure from your own policy, approved by the role Org Profile names (gov.exception_approver), with compensating controls and an expiry. It is not a risk acceptance: acceptance belongs to the business owner the record names.
A6: 1. Exception types
A7: Type | C7: Description | F7: Approval required | I7: Maximum duration | K7: Renewal
A8: Severe tool | C8: A Severe-risk tool approved for use (prohibited by default) | F8: CISO, committee and executive sponsor | I8: 12 months | K8: Required
A9: Guardrail bypass | C9: A required guardrail cannot be implemented yet | F9: Committee | I9: 6 months | K9: Required
A10: Vendor risk | C10: The vendor does not meet the assessment criteria | F10: Committee and Legal | I10: 6 months | K10: Required
A11: Compliance gap | C11: A framework control cannot be satisfied | F11: Committee and Compliance | I11: Until remediated | K11: Review at 90 days
A12: Emergency use | C12: Urgent business need; expedited review | F12: CISO, 48-hour retroactive | I12: 30 days | K12: Convert or close
A13: Model version | C13: A new model version deployed before the full evaluation suite passes | F13: Security and platform lead | I13: 14 days | K13: Convert on evaluation pass
A14: Pilot (agentic or internal build) | C14: An agentic tool or an internal build running with a restricted cohort before full approval | F14: Committee | I14: 60 days | K14: Convert or decommission
A15: Approver of record | C15: ="From Org Profile: "&'Org Profile'!C39&". The approval column above is the starter routing by type; the approver of record signs every exception." -> From Org Profile: CISO. The approval column above is the starter routing by type; the approver of record signs every exception.
A17: 2. Status legend
A18: Active | C18: Exception in effect; compensating controls monitored
A19: Renewal due | C19: Expires within 30 days; renewal required
A20: Expired | C20: Expired; the tool is decommissioned or re-approved
A21: Closed | C21: No longer needed: decommissioned, or converted to standard approval
A22: Rejected | C22: The approver denied the request
A24: 3. Exception log
A25: Exception ID | B25: Record ID | C25: Tool name | D25: Type | E25: Risk | F25: Guardrails affected | G25: Business justification | H25: Compensating controls | I25: Requester | J25: Approvers and vote | K25: Approved | L25: Expires | M25: Renewal | N25: Status | O25: Audit notes | P25: Related incidents
A26: EXC-2026-001 | B26: AIR-2026-OPSAGENT | C26: Operations agent (pilot) | D26: Pilot (agentic or internal build) | E26: Severe | F26: NHI-09 Autonomous action limits, NHI-08 Sub-agent spawn limits | G26: Pilot of an agentic platform for the operations team with a restricted cohort | H26: A person approves every external action; 24/7 monitoring; kill switch tested | I26: P. Lee | J26: CISO, committee 5-0, CTO | K26: 2026-06-01 | L26: 2026-10-01 | M26: Scheduled | N26: Renewal due | O26: Weekly review; convert to standard on pass | P26: None
A27: EXC-2026-002 | B27: AIR-2026-CLAUDE | C27: Claude Enterprise | D27: Model version | E27: Medium | F27: SUP-03 Model rollback procedure | G27: Model upgrade before the full evaluation suite passed; rollback ready | H27: Canary at 5 percent; hourly metrics; rollback runbook tested | I27: P. Lee | J27: Security and platform lead | K27: 2026-03-10 | L27: 2026-03-24 | M27: Converted | N27: Closed | O27: Evaluation suite passed 2026-03-21 | P27: None
A28: EXC-2026-003 | B28: AIR-2026-SFDC-AI | C28: Salesforce Agentforce | D28: Guardrail bypass | E28: High | F28: NHI-07 Tool and function authorization | G28: Vendor feature arrived on by default; tool catalog allowlisting not available at the current plan | H28: Agent actions limited to drafts; weekly log review; upgrade quoted | I28: A. Williams | J28: Committee 4-1 | K28: 2026-08-25 | L28: 2027-02-25 | M28: Pending | N28: Active | O28: Review when the plan upgrade lands | P28: None
A29: EXC-2025-004 | B29: AIR-2025-SUPPORTBOT | C29: Emergency chatbot | D29: Emergency use | E29: Medium | F29: RUN-01 Input validation, RUN-02 Output filtering | G29: Support surge after an outage; needed inside 24 hours | H29: Manual review of flagged conversations for the first 14 days | I29: K. Davis | J29: CISO, 48-hour retroactive | K29: 2025-11-01 | L29: 2025-12-01 | M29: Not applicable | N29: Closed | O29: Converted to standard approval in November 2025 | P29: None
A39: 4. Renewal process
A40: Step | B40: Action | G40: Owner | I40: Timeline
A41: 1 | B41: Submit the renewal with an updated justification | G41: Tool owner | I41: 30 days before expiry
A42: 2 | B42: Verify the compensating controls still work | G42: Security analyst | I42: Within 5 days
A43: 3 | B43: Document any incident during the exception period | G43: Security analyst | I43: With the renewal
A44: 4 | B44: Approver or committee reviews and the vote is recorded | G44: Approver of record | I44: Next scheduled meeting
A45: 5 | B45: Update the exception record with the new dates | G45: Security admin | I45: Within 2 days of the decision
A46: 6 | B46: Tell the requester and the business owner the outcome | G46: Security admin | I46: Same day
A48: 5. Where else this shows up
A49: Org Profile section 2 | C49: Who approves exceptions, who accepts risk, and the review cadence per level
A50: Tool Registry | C50: The Exception # and Record ID columns link the tool to its exception
A51: Guardrail Checklist | C51: Which guardrail is being bypassed, by ID
A52: The assessment record | C52: An exception is proposed in section 8 and routed to the approver of record; it is logged here once granted

Sheet AI Security Tool Landscape
A1: AI Security Risk Workbook: AI Security Tool Landscape
A3: A showcase of the market, not a shortlist. About 100 vendors mapped to the seven families as primary, secondary and tertiary coverage, so you can see overlap and avoid paying twice for the same thing. In your own records the skill names the tools you already own (Org Profile section 3) and points here only for a family with no coverage. Statuses and acquisitions checked against public M&A reporting through September 2026. Vendor positioning changes monthly; confirm before buying. Vendor and product names identify products and do not imply endorsement of, or affiliation with, any vendor.
A6: 1. The seven families
A7: Your tools for each family come from Org Profile section 3. Change them there.
A8: Family | C8: What it covers | G8: Guardrails | H8: Your tools
A9: AI Posture & Governance | C9: Inventory, risk classification, approval, policy, vendor and compliance review | G9: 8 (POS) | H9: ='Org Profile'!C63 -> 0
A10: Runtime Protection & Guardrails | C10: Prompt injection and jailbreak defense, output filtering, content safety, rate and cost limits, egress control | G10: 9 (RUN) | H10: ='Org Profile'!C64 -> 0
A11: Shadow AI & Usage Discovery | C11: Finding AI use you did not sanction, tracking who uses what, blocking personal accounts | G11: 5 (SHA) | H11: ='Org Profile'!C65 -> 0
A12: Observability & Evaluation | C12: Audit logging, retention, SIEM, alerting, drift and hallucination monitoring, red teaming, bias testing, agent behavior monitoring | G12: 8 (OBS) | H12: ='Org Profile'!C66 -> 0
A13: Data Protection for AI | C13: DLP, PII detection, classification, encryption, masking, retention, training opt-out, provenance marking, user disclosure | G13: 10 (DAT) | H13: ='Org Profile'!C67 -> 0
A14: NHI & Agentic Access | C14: Service accounts, secrets, rotation, short-lived tokens, agent identity, intent and tool authorization, spawn limits, autonomy limits, boundaries, sandboxes, memory | G14: 12 (NHI) | H14: ='Org Profile'!C68 -> 0
A15: AI Supply Chain | C15: Model provenance, pinning, rollback, training data lineage and consent, pipeline security, integrity checks, third-party models, plugins and MCP servers, vector stores, system prompts, embeddings, action attestation | G15: 13 (SUP) | H15: ='Org Profile'!C69 -> 0
A17: 2. What changed in 2026
A18: Consolidation kept its pace. Palo Alto Networks closed CyberArk ($25B, February) and added Koi and Portkey to Prisma AIRS. Google closed Wiz ($32B, March). Cisco bought Astrix, Galileo and WideField. Cyera bought Oasis Security (about $1B, July) and became the one vendor that owns both DSPM and agent identity. SailPoint took Entro, Okta took Permiso, 1Password took Apono, Delinea took StrongDM, CrowdStrike took SGNL: every identity platform now has an agent story. Akamai bought LayerX, Proofpoint bought Acuvity, Zscaler bought Symmetry, Varonis bought AllTrue.ai, Fortinet bought Virtue AI, A10 bought TrojAI, Check Point added Cyata and Deepchecks, F5 added SurePath, OpenAI took Promptfoo and Harvey took Guardrails AI. The independents that raised: HiddenLayer ($100M, September), WitnessAI ($58M, January), Harmonic ($50M), Cyera ($400M at $9B). MCP security arrived as a category of its own (Runlayer, Helmet, Operant, plus gateway features from Cloudflare and Microsoft). Before buying a point tool, check whether a platform you already pay for now includes the capability.
A20: 3. Vendor landscape
A21: table:vendors | B21: Vendor (product) | C21: Status | D21: Deployment | E21: Pricing tier | F21: Primary family | G21: Secondary family | H21: Tertiary family | I21: Summary | J21: Best for
A22: vendors | B22: Palo Alto Networks (Prisma AIRS, Protect AI, Portkey, Koi) | C22: Platform | D22: Platform | E22: Enterprise | F22: Runtime Protection & Guardrails | G22: AI Supply Chain | H22: NHI & Agentic Access | I22: Prisma AIRS bundles Protect AI (model scanning, supply chain, red teaming), Portkey (AI gateway, agreed April 2026, roughly $120M to $140M) and Koi (agentic endpoint security, February 2026, about $400M) with CyberArk identity (closed February 2026, $25B). The widest single-vendor AI security stack today. | J22: Palo Alto customers wanting one platform across runtime, supply chain and identity
A23: vendors | B23: Cisco (AI Defense, Robust Intelligence, Astrix, Galileo, WideField) | C23: Platform | D23: Platform | E23: Enterprise | F23: AI Posture & Governance | G23: NHI & Agentic Access | H23: Observability & Evaluation | I23: Cisco AI Defense grew out of Robust Intelligence (2024) and added Astrix non-human identity (May 2026, about $400M), Galileo evaluation and observability (April 2026) and WideField identity threat detection (June 2026). Agent identity and observability land in Splunk and Duo. | J23: Cisco and Splunk shops; agent identity and evaluation under one roof
A24: vendors | B24: Microsoft (Defender for Cloud, Purview, Entra Agent ID, Agent 365) | C24: Platform | D24: Platform | E24: Included in platform | F24: AI Posture & Governance | G24: Data Protection for AI | H24: NHI & Agentic Access | I24: AI-SPM in Defender for Cloud, DLP for Copilot and GenAI apps in Purview, agent identities in Entra Agent ID, and Agent 365 as the control plane and MCP gateway for agents in M365. The default answer for an M365 tenant before buying point tools. | J24: Azure and M365 shops; Copilot governance
A25: vendors | B25: Google Cloud (Wiz, Wiz Code, Model Armor, Vertex AI safety) | C25: Platform | D25: Platform | E25: Enterprise | F25: AI Posture & Governance | G25: Runtime Protection & Guardrails | H25: AI Supply Chain | I25: Google closed the $32B Wiz acquisition on March 11, 2026. Wiz keeps multicloud AI-SPM and attack-path analysis, Wiz Code covers code-side AI risk, Model Armor screens prompts and responses, and Vertex AI carries the safety filters. | J25: Wiz customers; GCP and Vertex AI workloads
A26: vendors | B26: AWS (Bedrock Guardrails, Bedrock AgentCore) | C26: Platform | D26: Platform | E26: Included in platform | F26: Runtime Protection & Guardrails | G26: NHI & Agentic Access | H26: Observability & Evaluation | I26: Bedrock Guardrails screens prompts and outputs with Automated Reasoning checks. AgentCore gives agents a managed runtime with identity, tool authorization, memory isolation and observability. | J26: AWS-native agent and model deployments
A27: vendors | B27: CrowdStrike (Pangea, SGNL, Seraphic) | C27: Platform | D27: Platform | E27: Enterprise | F27: Runtime Protection & Guardrails | G27: NHI & Agentic Access | H27: AI Posture & Governance | I27: Pangea (2025, about $260M) became AI Detection and Response in Falcon. SGNL (January 2026, $740M) adds continuous authorization for humans, machines and agents. Seraphic (January 2026, about $420M) adds in-session browser protection for AI interactions. | J27: CrowdStrike customers; endpoint-centric programs adding agent authorization
A28: vendors | B28: Check Point (Lakera, Cyata, Deepchecks) | C28: Platform | D28: Platform | E28: Enterprise | F28: Runtime Protection & Guardrails | G28: AI Posture & Governance | H28: Observability & Evaluation | I28: Lakera (closed late 2025, about $300M) is the runtime guardrail layer in Infinity. Cyata (February 2026) and Deepchecks (May 2026, LLM evaluation) extend it toward agent security and continuous evaluation. | J28: Check Point customers; prompt injection, data leakage and MCP or RAG flow protection
A29: vendors | B29: SentinelOne (Prompt Security, Observo) | C29: Platform | D29: Platform | E29: Enterprise | F29: Shadow AI & Usage Discovery | G29: Runtime Protection & Guardrails | H29: Data Protection for AI | I29: Prompt Security (September 2025, $133.6M) covers employee GenAI visibility, browser-level controls and prompt protection. Observo (about $225M) handles the telemetry pipeline. Purple AI ties them together. | J29: SentinelOne customers; employee GenAI usage governance
A30: vendors | B30: Zscaler (Symmetry Systems) | C30: Public | D30: Platform | E30: Enterprise | F30: Data Protection for AI | G30: Shadow AI & Usage Discovery | H30: Runtime Protection & Guardrails | I30: Zero trust exchange with GenAI app control, shadow AI discovery and data protection. Symmetry Systems (May 2026) adds access mapping of what data AI agents can reach and least-privilege data policy. | J30: Zscaler customers; SASE-delivered AI data controls
A31: vendors | B31: Netskope | C31: Public | D31: Platform | E31: Enterprise | F31: Data Protection for AI | G31: Shadow AI & Usage Discovery | H31: Runtime Protection & Guardrails | I31: SASE with GenAI-aware DLP, real-time user coaching and app risk scoring for AI services. Public since September 2025. | J31: Netskope customers; coaching users at the point of use
A32: vendors | B32: Proofpoint (Acuvity, Normalyze) | C32: Platform | D32: Platform | E32: Enterprise | F32: Shadow AI & Usage Discovery | G32: Data Protection for AI | H32: AI Posture & Governance | I32: Acuvity (February 2026) brings real-time visibility and control over how employees and systems use AI apps. Normalyze (2024) brings DSPM. Together they cover discovery, data flows into AI and policy enforcement. | J32: Proofpoint customers; human-centric AI usage controls
... A43: vendors | B43: Cloudflare (AI Gateway, Firewall for AI, MCP support) | C43: Platform | D43: Platform | E43: Free + Enterprise | F43: Runtime Protection & Guardrails | G43: Observability & Evaluation | H43: NHI & Agentic Access | I43: AI Gateway gives caching, rate limits, logging and cost controls in front of any model. Firewall for AI screens prompts. MCP hosting and gateway features cover remote MCP servers. | J43: Teams fronting many models and MCP servers through one edge
A44: vendors | B44: NVIDIA NeMo Guardrails | C44: Platform | D44: Both | E44: Free + Enterprise | F44: Runtime Protection & Guardrails | G44: Observability & Evaluation | I44: Programmable guardrails and inference microservices for LLM apps. | J44: NVIDIA ecosystem and self-hosted inference
A45: vendors | B45: Anthropic built-in safety | C45: Platform | D45: Platform | E45: Included in platform | F45: Runtime Protection & Guardrails | I45: Provider-side safeguards in the Claude API and Claude apps: classifiers, content safety, agent skill sandboxing, enterprise data controls. | J45: Teams running Claude as the primary model
A46: vendors | B46: OpenAI Moderation API and enterprise controls | C46: Platform | D46: Platform | E46: Free / included | F46: Runtime Protection & Guardrails | G46: Data Protection for AI | I46: Hosted content moderation usable with any model, plus enterprise data controls. Promptfoo (March 2026) brought adversarial testing into the Frontier platform. | J46: Teams wanting a free moderation layer or running on OpenAI
A47: vendors | B47: Azure AI Content Safety | C47: Platform | D47: Platform | E47: Included in platform | F47: Runtime Protection & Guardrails | G47: Data Protection for AI | H47: AI Posture & Governance | I47: Microsoft-hosted content safety with Prompt Shields, groundedness detection and protected-material detection. | J47: Azure OpenAI and Copilot ecosystem
A48: vendors | B48: Datadog LLM Observability | C48: Platform | D48: SaaS | E48: Team + Enterprise | F48: Observability & Evaluation | G48: AI Posture & Governance | I48: LLM monitoring with prompt injection detection, PII scanning, cost tracking and traces in the existing Datadog tenant. | J48: Datadog customers
A49: vendors | B49: Sysdig | C49: Public | D49: SaaS | E49: Enterprise | F49: Observability & Evaluation | G49: Runtime Protection & Guardrails | H49: AI Posture & Governance | I49: Runtime observability for AI workloads: container-level visibility into model-serving infrastructure and agent runtimes. | J49: Kubernetes shops running their own inference
A50: vendors | B50: JFrog | C50: Public | D50: Both | E50: Enterprise | F50: AI Supply Chain | G50: AI Posture & Governance | I50: Universal artifact repository with ML model management, SBOM and DevSecOps controls. | J50: JFrog customers; artifact management for models
A51: vendors | B51: Noma Security | C51: Independent | D51: SaaS | E51: Enterprise | F51: AI Posture & Governance | G51: AI Supply Chain | H51: NHI & Agentic Access | I51: Full AI lifecycle security with a strong agentic focus: discovery, supply chain, runtime and agent governance. $100M Series B in July 2025, $132M raised. | J51: Comprehensive AI security; agentic deployments
A52: vendors | B52: HiddenLayer | C52: Independent | D52: SaaS | E52: Enterprise | F52: AI Supply Chain | G52: Runtime Protection & Guardrails | H52: AI Posture & Governance | I52: Model scanning across about 50 file formats, supply chain security, attack simulation and runtime protection extended to prompt injection, agent manipulation and malicious tool use. $100M Series B in September 2026. | J52: Open-weight model consumers; independent vendor preference
A53: vendors | B53: Zenity | C53: Independent | D53: SaaS | E53: Enterprise | F53: AI Posture & Governance | G53: NHI & Agentic Access | H53: Runtime Protection & Guardrails | I53: Agent-centric posture management with a low-code and Copilot Studio specialty. More than $100M raised. | J53: Organizations deploying agents at scale on M365 and low-code platforms
A54: vendors | B54: WitnessAI | C54: Independent | D54: SaaS | E54: Enterprise | F54: AI Posture & Governance | G54: Shadow AI & Usage Discovery | H54: Runtime Protection & Guardrails | I54: Discovers AI usage, enforces policy and coaches users on safe practice. $58M Series B in January 2026, $85.5M raised. | J54: Safe AI enablement with visibility and coaching
A55: vendors | B55: Credo AI | C55: Independent | D55: SaaS | E55: Enterprise | F55: AI Posture & Governance | G55: Observability & Evaluation | H55: AI Supply Chain | I55: AI governance platform: policies, risk assessments, model inventory and supply chain tracking. | J55: AI governance and vendor risk management teams
A56: vendors | B56: Holistic AI | C56: Independent | D56: SaaS | E56: Enterprise | F56: AI Posture & Governance | G56: Observability & Evaluation | I56: End-to-end AI risk management: live inventory, EU AI Act alignment, bias auditing. | J56: EU AI Act compliance programs
A57: vendors | B57: Cranium AI (Aiceberg) | C57: Independent | D57: SaaS | E57: Enterprise | F57: AI Posture & Governance | G57: AI Supply Chain | H57: Observability & Evaluation | I57: AI security governance and agentic AI platform. Acquired Aiceberg in May 2026. | J57: Governance-led programs
A58: vendors | B58: Pillar Security | C58: Independent | D58: SaaS | E58: Enterprise | F58: AI Posture & Governance | G58: Runtime Protection & Guardrails | H58: Observability & Evaluation | I58: End-to-end GenAI security: discovery, risk assessment, runtime protection, evaluation. | J58: Organizations wanting one consolidated GenAI security vendor
A59: vendors | B59: Apex Security | C59: Independent | D59: SaaS | E59: Enterprise | F59: Shadow AI & Usage Discovery | G59: Data Protection for AI | H59: AI Posture & Governance | I59: GenAI security platform: discovery, policy enforcement and risk scoring per AI app. | J59: Mid-market shadow AI and DLP consolidation
A60: vendors | B60: Legit Security | C60: Independent | D60: SaaS | E60: Enterprise | F60: AI Supply Chain | G60: AI Posture & Governance | H60: Runtime Protection & Guardrails | I60: ASPM with AI code security, model supply chain and SDLC controls for ML. | J60: DevSecOps teams; AI in the software supply chain
A61: vendors | B61: Cycode | C61: Independent | D61: SaaS | E61: Enterprise | F61: AI Posture & Governance | G61: AI Supply Chain | H61: Runtime Protection & Guardrails | I61: ASPM with AI-native code security, pipeline security and secrets detection. | J61: ASPM-first organizations
A62: vendors | B62: Arthur AI | C62: Independent | D62: Both | E62: Enterprise | F62: Runtime Protection & Guardrails | G62: Observability & Evaluation | H62: AI Posture & Governance | I62: LLM firewall and observability with a federated architecture that keeps data local. | J62: Regulated industries; data residency requirements
A63: vendors | B63: Mindgard | C63: Independent | D63: SaaS | E63: Enterprise | F63: Runtime Protection & Guardrails | G63: Observability & Evaluation | H63: AI Supply Chain | I63: Offensive AI security: automated red teaming, vulnerability scanning and supply chain testing. | J63: Continuous AI security testing
A64: vendors | B64: Prompt Armor | C64: Independent | D64: SaaS | E64: Enterprise | F64: Runtime Protection & Guardrails | G64: Data Protection for AI | H64: Observability & Evaluation | I64: Prompt injection firewall with real-time threat detection for LLM apps. | J64: Dedicated prompt security; API-first deployment
A65: vendors | B65: Straiker (Defend AI) | C65: Independent | D65: SaaS | E65: Enterprise | F65: Runtime Protection & Guardrails | G65: NHI & Agentic Access | H65: Observability & Evaluation | I65: Agentic AI runtime security: context-aware guardrails across prompts, reasoning and tool calls. | J65: Production agentic AI
A66: vendors | B66: Tumeryk | C66: Independent | D66: SaaS | E66: Enterprise | F66: Runtime Protection & Guardrails | G66: NHI & Agentic Access | H66: Observability & Evaluation | I66: Runtime guardrails plus agent-specific behavior monitoring. Early stage, purpose-built for agents. | J66: Organizations deploying production agents
A67: vendors | B67: Lasso Security | C67: Independent | D67: SaaS | E67: Enterprise | F67: Runtime Protection & Guardrails | G67: Shadow AI & Usage Discovery | H67: Data Protection for AI | I67: LLM and agent security: visibility of GenAI use, prompt and response protection, policy enforcement. | J67: GenAI usage security for the workforce and apps
A68: vendors | B68: Dynamo AI | C68: Independent | D68: Both | E68: Enterprise | F68: Runtime Protection & Guardrails | G68: Data Protection for AI | H68: Observability & Evaluation | I68: Compliance-focused GenAI: PII redaction, policy enforcement and regulated-industry tooling. | J68: Finance and healthcare
A69: vendors | B69: Hex Security | C69: Independent | D69: SaaS | E69: Enterprise | F69: Runtime Protection & Guardrails | G69: AI Posture & Governance | I69: AI agents running continuous penetration tests for vulnerability discovery. | J69: Continuous security testing
A70: vendors | B70: LLM Guard (Protect AI, open source) | C70: Open source | D70: OSS | E70: Free / OSS | F70: Runtime Protection & Guardrails | G70: Data Protection for AI | I70: Open source input and output scanner: PII, toxicity, prompt injection. Maintained under Palo Alto Networks since the Protect AI acquisition. | J70: OSS-first teams building their own guardrail layer
A71: vendors | B71: Guardrails AI (Harvey) | C71: Acquired (Harvey, September 2026) | D71: OSS | E71: Free / OSS | F71: Runtime Protection & Guardrails | G71: Observability & Evaluation | I71: Open source validators for prompt injection, PII, toxicity and structured output. Harvey acquired the team in September 2026 and is sunsetting the hub; pin validator versions if you depend on it. | J71: Existing users; plan a migration
A72: vendors | B72: Promptfoo (OpenAI) | C72: Acquired (OpenAI, March 2026) | D72: OSS | E72: Free / OSS | F72: Observability & Evaluation | G72: Runtime Protection & Guardrails | I72: Open source LLM and agent testing with simulated adversarial attacks, now part of OpenAI's Frontier platform. The OSS project remains the common red-team harness. | J72: Teams scripting red-team and eval runs in CI
A73: vendors | B73: Harmonic Security | C73: Independent | D73: SaaS | E73: Enterprise | F73: Shadow AI & Usage Discovery | G73: Data Protection for AI | H73: AI Posture & Governance | I73: Shadow AI discovery with GenAI-aware DLP and workforce AI protection. Raised $50M in 2026. | J73: DLP tuned for how people use GenAI
A74: vendors | B74: Nightfall AI | C74: Independent | D74: SaaS | E74: Enterprise | F74: Shadow AI & Usage Discovery | G74: Data Protection for AI | H74: Runtime Protection & Guardrails | I74: AI-native DLP plus a GenAI firewall. | J74: Cloud-native DLP for AI apps
A75: vendors | B75: Reco | C75: Independent | D75: SaaS | E75: Enterprise | F75: Shadow AI & Usage Discovery | G75: Data Protection for AI | H75: AI Posture & Governance | I75: SaaS security with AI discovery: finds AI apps, tracks data flows, enforces policy. | J75: SaaS security teams extending to AI
A76: vendors | B76: Island (enterprise browser) | C76: Independent | D76: SaaS | E76: Enterprise | F76: Data Protection for AI | G76: Shadow AI & Usage Discovery | H76: AI Posture & Governance | I76: Enterprise browser with AI controls: DLP, session recording, app isolation. | J76: Browser-based control of AI use
A77: vendors | B77: Cyera (Oasis Security, Ryft, Genie) | C77: Independent | D77: SaaS | E77: Enterprise | F77: Data Protection for AI | G77: NHI & Agentic Access | H77: AI Posture & Governance | I77: DSPM leader that bought Oasis non-human identity (July 2026, about $1B), Ryft agent data lake security (April 2026) and Genie endpoint data protection for GenAI (May 2026). $400M Series F in January 2026 at a $9B valuation. | J77: Enterprise DSPM; data plus agent identity in one vendor
A78: vendors | B78: BigID | C78: Independent | D78: Both | E78: Enterprise | F78: Data Protection for AI | G78: AI Posture & Governance | H78: Shadow AI & Usage Discovery | I78: Data discovery and governance with shadow AI detection and AI model inventory. | J78: Data discovery and governance for AI
A79: vendors | B79: Knostic | C79: Independent | D79: SaaS | E79: Enterprise | F79: Data Protection for AI | G79: AI Posture & Governance | H79: Runtime Protection & Guardrails | I79: Need-to-know access for AI: context-aware data protection and RAG security. | J79: RAG and enterprise search deployments
A80: vendors | B80: Protecto | C80: Independent | D80: SaaS | E80: Team + Enterprise | F80: Data Protection for AI | G80: Runtime Protection & Guardrails | I80: Privacy layer for AI: PII detection, tokenization and masking for prompts, RAG and fine-tuning data. | J80: Privacy-preserving data flows into AI
A81: vendors | B81: TrustLogix | C81: Independent | D81: SaaS | E81: Enterprise | F81: Data Protection for AI | G81: AI Posture & Governance | I81: Data access governance for AI: who and what can reach which data, enforced across platforms. | J81: Data access governance ahead of AI rollouts
A82: vendors | B82: GitGuardian | C82: Independent | D82: SaaS | E82: Team + Enterprise | F82: Data Protection for AI | G82: AI Supply Chain | H82: NHI & Agentic Access | I82: Secrets detection extended to LLM context: secrets in prompts, agent memory and RAG corpora. | J82: Teams worried about secrets leaking into context windows
A83: vendors | B83: Kiteworks (Bonfy.AI) | C83: Platform | D83: Both | E83: Enterprise | F83: Data Protection for AI | G83: AI Posture & Governance | I83: Bonfy.AI (September 2026) adds real-time policy enforcement over sensitive data exchanged by people and agents. | J83: Kiteworks customers
A84: vendors | B84: Arize AI | C84: Independent | D84: Both | E84: Team + Enterprise | F84: Observability & Evaluation | G84: AI Posture & Governance | H84: Runtime Protection & Guardrails | I84: Enterprise AI observability: Phoenix open source plus the AX platform. | J84: Production ML and LLM monitoring
A85: vendors | B85: Patronus AI | C85: Independent | D85: SaaS | E85: Enterprise | F85: Observability & Evaluation | G85: Runtime Protection & Guardrails | H85: AI Posture & Governance | I85: LLM evaluation: hallucination detection and automated testing. | J85: LLM quality assurance
A86: vendors | B86: Fiddler AI | C86: Independent | D86: Both | E86: Enterprise | F86: Observability & Evaluation | G86: AI Posture & Governance | H86: Data Protection for AI | I86: Model scoring, guardrails and explainability for LLMs. | J86: Regulated industries needing explainability
A87: vendors | B87: LangSmith (LangChain) | C87: Independent | D87: Both | E87: Team + Enterprise | F87: Observability & Evaluation | G87: AI Posture & Governance | I87: LLM app debugging and monitoring: traces, evaluations, prompt management. | J87: LangChain and LangGraph users
A88: vendors | B88: Weights & Biases (CoreWeave) | C88: Acquired (CoreWeave, 2025) | D88: Both | E88: Team + Enterprise | F88: Observability & Evaluation | G88: AI Posture & Governance | I88: MLOps platform: experiment tracking, model registry, LLM tracing. | J88: ML teams; experiment tracking
A89: vendors | B89: Galileo (Cisco) | C89: Acquired (Cisco, April 2026) | D89: SaaS | E89: Enterprise | F89: Observability & Evaluation | G89: Runtime Protection & Guardrails | H89: Data Protection for AI | I89: LLM and agent evaluation: hallucination, data quality, guardrails. Now part of Cisco's AI observability push with Splunk. | J89: Cisco customers; LLM debugging
A90: vendors | B90: Portkey (Palo Alto Networks) | C90: Acquired (Palo Alto Networks, April 2026) | D90: SaaS | E90: Team + Enterprise | F90: Observability & Evaluation | G90: Runtime Protection & Guardrails | H90: NHI & Agentic Access | I90: AI gateway and observability: unified API, caching, fallbacks, cost management, agent control plane. Folding into Prisma AIRS. | J90: Multi-LLM deployments; gateway control of agents
A91: vendors | B91: Helicone | C91: Open source | D91: Both | E91: Free / Team | F91: Observability & Evaluation | G91: AI Posture & Governance | I91: Open source LLM observability: logging, caching, rate limiting. | J91: OSS-first LLM monitoring on a budget
A92: vendors | B92: Langfuse | C92: Open source | D92: Both | E92: Free + Team | F92: Observability & Evaluation | G92: AI Posture & Governance | I92: Open source LLM observability: tracing, prompt management, evaluation. | J92: OSS-first teams
A93: vendors | B93: Comet Opik | C93: Open source | D93: Both | E93: Free + Team | F93: Observability & Evaluation | G93: Runtime Protection & Guardrails | I93: LLM evaluation and monitoring: quality, performance drift. | J93: ML teams; quality assurance
A94: vendors | B94: Braintrust | C94: Independent | D94: SaaS | E94: Team + Enterprise | F94: Observability & Evaluation | G94: AI Posture & Governance | I94: Production traces to evaluation cases, with results on pull requests. | J94: LLM app teams iterating on quality
A95: vendors | B95: Maxim AI | C95: Independent | D95: SaaS | E95: Enterprise | F95: Observability & Evaluation | G95: AI Posture & Governance | H95: Runtime Protection & Guardrails | I95: Agent lifecycle platform: experimentation, simulation, evaluation, observability. | J95: Agent development teams
A96: vendors | B96: Deepchecks (Check Point) | C96: Acquired (Check Point, May 2026) | D96: Both | E96: Team + Enterprise | F96: Observability & Evaluation | G96: Runtime Protection & Guardrails | I96: Continuous monitoring and LLM evaluation, now used to validate Check Point's agentic security tools. | J96: Check Point customers; evaluation
A97: vendors | B97: Radiant Security (Cribl) | C97: Acquired (Cribl, August 2026) | D97: SaaS | E97: Enterprise | F97: Observability & Evaluation | G97: AI Posture & Governance | H97: Runtime Protection & Guardrails | I97: AI-native SOC with autonomous triage and response. Adjacent: AI for security operations rather than security for AI. | J97: SOC teams reducing alert fatigue
A98: vendors | B98: Prophet Security | C98: Independent | D98: SaaS | E98: Enterprise | F98: Observability & Evaluation | G98: AI Posture & Governance | I98: Agentic SOC: autonomous investigation and response. Adjacent category. | J98: SOC teams; autonomous investigation
A99: vendors | B99: Simbian | C99: Independent | D99: SaaS | E99: Enterprise | F99: Observability & Evaluation | G99: Runtime Protection & Guardrails | H99: AI Posture & Governance | I99: Autonomous agents for security operations. Adjacent category. | J99: SOC teams; autonomous investigation
A100: vendors | B100: Silverfort (Fabrix) | C100: Independent | D100: SaaS | E100: Enterprise | F100: NHI & Agentic Access | G100: Shadow AI & Usage Discovery | H100: AI Posture & Governance | I100: Unified human and non-human identity security with NHI visibility. Fabrix (April 2026) adds an AI decisioning engine across human, machine and agentic identities. | J100: Enterprise IAM extending to NHI and agents
A101: vendors | B101: Astrix Security (Cisco) | C101: Acquired (Cisco, May 2026) | D101: SaaS | E101: Enterprise | F101: NHI & Agentic Access | G101: Shadow AI & Usage Discovery | H101: AI Posture & Governance | I101: Dedicated NHI platform: agent inventory, least privilege, token monitoring. Folding into Cisco Identity Intelligence, Duo and Splunk. | J101: NHI-first programs on Cisco
A102: vendors | B102: Oasis Security (Cyera) | C102: Acquired (Cyera, July 2026) | D102: SaaS | E102: Enterprise | F102: NHI & Agentic Access | G102: Shadow AI & Usage Discovery | H102: AI Posture & Governance | I102: NHI Security Cloud with Agentic Access Management and intent-based access control, now the identity half of Cyera. | J102: Agentic access control alongside DSPM
A103: vendors | B103: Aembit | C103: Independent | D103: SaaS | E103: Enterprise | F103: NHI & Agentic Access | G103: Shadow AI & Usage Discovery | H103: Data Protection for AI | I103: Secretless workload IAM: workload-to-workload and agent identity without long-lived credentials. | J103: Secretless architecture for agents and services
A104: vendors | B104: Entro Security (SailPoint) | C104: Acquired (SailPoint, June 2026) | D104: SaaS | E104: Enterprise | F104: NHI & Agentic Access | G104: Shadow AI & Usage Discovery | H104: AI Posture & Governance | I104: Secrets and non-human identity discovery, including exposed AI API keys, now inside SailPoint's Agentic Fabric. | J104: Secrets sprawl; credential exposure
A105: vendors | B105: CyberArk (Palo Alto Networks) | C105: Acquired (Palo Alto Networks, February 2026) | D105: Both | E105: Enterprise | F105: NHI & Agentic Access | G105: AI Posture & Governance | H105: Data Protection for AI | I105: PAM and machine identity security, now part of Palo Alto Networks. The platform stays standalone while capabilities integrate into Prisma and Cortex. | J105: Enterprise PAM; machine and agent identities
A106: vendors | B106: HashiCorp Vault (IBM) | C106: Acquired (IBM, 2025) | D106: Both | E106: Free + Enterprise | F106: NHI & Agentic Access | G106: Data Protection for AI | I106: Secrets management: dynamic secrets, encryption, identity-based access. | J106: Secrets management; dynamic credentials for agents
A107: vendors | B107: Spec | C107: Independent | D107: SaaS | E107: Enterprise | F107: NHI & Agentic Access | G107: Runtime Protection & Guardrails | H107: AI Posture & Governance | I107: Agentic security platform: agent identity, behavior monitoring, response. | J107: Organizations with production agents
A108: vendors | B108: Strata Identity (Rubrik) | C108: Acquired (Rubrik, June 2026) | D108: SaaS | E108: Enterprise | F108: NHI & Agentic Access | G108: AI Posture & Governance | I108: Identity orchestration with failover to a secondary identity provider and policy-based agent permissions. | J108: Identity resilience; agentic identity policy
A109: vendors | B109: Keycard | C109: Independent | D109: SaaS | E109: Team + Enterprise | F109: NHI & Agentic Access | G109: AI Posture & Governance | I109: Identity and access for AI agents and autonomous coding agents. Acquired Anchor.dev in February 2026. | J109: Developer teams issuing identities to coding agents
A110: vendors | B110: Keyfactor (Cofide) | C110: Platform | D110: Both | E110: Enterprise | F110: NHI & Agentic Access | G110: AI Supply Chain | I110: Cofide (July 2026) brings verified identity for agents and cloud workloads into Keyfactor's machine identity platform. | J110: PKI and workload identity for agents
A111: vendors | B111: Runlayer | C111: Independent | D111: SaaS | E111: Team + Enterprise | F111: NHI & Agentic Access | G111: AI Supply Chain | H111: Runtime Protection & Guardrails | I111: MCP security gateway: authentication, authorization and logging for MCP servers and the agents that call them. $11M seed in November 2025. | J111: Teams standardizing on MCP
A112: vendors | B112: Helmet Security | C112: Independent | D112: SaaS | E112: Team + Enterprise | F112: AI Supply Chain | G112: NHI & Agentic Access | I112: MCP infrastructure security: server verification, policy and monitoring. $9M seed in December 2025. | J112: MCP server operators
A113: vendors | B113: Operant AI | C113: Independent | D113: Both | E113: Enterprise | F113: Runtime Protection & Guardrails | G113: NHI & Agentic Access | H113: AI Supply Chain | I113: Runtime protection for AI apps and MCP: live traffic inspection, agent and tool guardrails. | J113: Kubernetes-hosted AI apps and MCP servers
A114: vendors | B114: Invariant Labs (Snyk) | C114: Acquired (Snyk, June 2025) | D114: SaaS | E114: Enterprise | F114: Runtime Protection & Guardrails | G114: NHI & Agentic Access | H114: Observability & Evaluation | I114: Agent security testing and guardrails, now part of Snyk's AI Trust Platform with Evo agentic security and MCP server scanning. | J114: Snyk customers; agentic AI testing
A115: vendors | B115: Snyk (AI Trust Platform) | C115: Independent | D115: Both | E115: Team + Enterprise | F115: AI Supply Chain | G115: Runtime Protection & Guardrails | H115: AI Posture & Governance | I115: AI-BOM scanning, Evo agentic security, MCP server security, Invariant Labs guardrails. | J115: DevSecOps; AI-generated code and MCP supply chain
...

Sheet Compliance Mapping
A1: AI Security Risk Workbook: Compliance Mapping
A3: Every guardrail mapped to seven frameworks across eight columns (NIST AI RMF and its GenAI profile sit side by side). Use it for audit evidence and gap analysis, and the record cites the frameworks named on Org Profile (org.frameworks) for every guardrail in scope. The citations point to where the obligation or control lives; whether it applies to you depends on your role (provider or deployer under the EU AI Act, in scope or out for SOC 2) and your industry. Extend the mapping with your auditors for anything you certify against beyond these eight.
A6: 1. Framework reference
A7: Framework | C7: Full name and version | H7: How the column cites it
A8: CSA AICM | C8: Cloud Security Alliance AI Controls Matrix v1.1 (2026): 247 control objectives across 18 domains, CCM v4.1 plus Model Security (MDS) and AI-specific controls | H8: Control IDs as the AICM lists them (AIS-08, MDS-02, IAM-19). Use for shared-responsibility conversations with cloud and AI providers; the AI-CAIQ asks the same questions.
A9: EU AI Act | C9: Regulation (EU) 2024/1689. Prohibitions since 2 February 2025, GPAI duties since 2 August 2025, transparency duties (Art. 50) from 2 August 2026. The 2026 Digital Omnibus moved Annex III high-risk obligations to 2 December 2027 and Annex I to 2 August 2028; confirm the current dates before relying on them. | H9: Articles. Most high-risk duties (Art. 9 to 15) sit with the provider; a buyer meets them through Art. 26 deployer duties and the provider's documentation (Art. 13). Art. 25 covers the value chain and written agreements.
A10: ISO/IEC 42001 | C10: ISO/IEC 42001:2023 AI management system. Clauses 4 to 10, plus Annex A controls (A.2 to A.10) which are normative when selected in the Statement of Applicability | H10: Annex A control references (A.6.2.6, A.7.5, A.10.3) and clause numbers where the clause itself is the fit.
A11: MITRE ATLAS | C11: Adversarial Threat Landscape for AI Systems, data release 2026.09: 16 tactics, 208 techniques and sub-techniques, 40 mitigations, with the agentic additions from late 2025 onward | H11: Technique IDs (AML.T0051) the guardrail counters and mitigation IDs (AML.M0020) it implements. Use for threat modeling and red-team planning.
A12: NIST AI RMF | C12: NIST AI Risk Management Framework 1.0 (January 2023): GOVERN, MAP, MEASURE, MANAGE functions and their subcategories | H12: Subcategory IDs (GOVERN 1.6, MEASURE 2.7). The subcategory is the unit auditors and the GenAI profile key off.
A13: NIST AI 600-1 | C13: NIST AI 600-1 Generative AI Profile (July 2024): about 200 suggested actions keyed to RMF subcategories, addressing 12 GenAI risks | H13: The action group by subcategory (MS-2.7 actions) and the GenAI risk it addresses (Information Security, Data Privacy, Confabulation, Value Chain and Component Integration, and so on).
A14: OWASP | C14: OWASP Top 10 for LLM Applications 2025 (LLM01 to LLM10) and OWASP Top 10 for Agentic Applications 2026 (ASI01 to ASI10, released December 2025) | H14: Risk IDs with their names. Cite the LLM list for any model-backed app and add the ASI list when the agentic flag is set.
A15: SOC 2 | C15: AICPA Trust Services Criteria (2017, with 2022 points of focus): Common Criteria CC1 to CC9, Availability, Confidentiality, Processing Integrity, Privacy | H15: Criteria IDs (CC6.1, C1.1, PI1.4). Use when the tool is in scope for your own SOC 2, and to read a vendor's SOC 2 report against the guardrail.
A17: 2. Guardrail to framework mapping
A18: Filter by family or by ID. The ID column matches the Guardrail Checklist tab.
A19: table:compliance | B19: ID | C19: Family | D19: Guardrail | E19: CSA AICM | F19: EU AI Act | G19: ISO/IEC 42001 | H19: MITRE ATLAS | I19: NIST AI RMF | J19: NIST AI 600-1 | K19: OWASP | L19: SOC 2
A20: compliance | B20: POS-01 | C20: AI Posture & Governance | D20: Tool registration | E20: GRC-05 Information Security Program; DCS-06 Assets Cataloguing and Tracking; UEM-02 Application and Service Approval; STA-16 Service BOM | F20: Art. 26 deployer obligations (know and record what is in use); Art. 49 registration of high-risk systems; Art. 11 technical documentation (providers) | G20: A.4.2 Resource documentation; A.6.2.7 AI system technical documentation; A.9.4 Intended use | H20: AML.M0023 AI Bill of Materials; supports every other mitigation by naming what exists | I20: GOVERN 1.6 (inventory of AI systems); MAP 1.1 (context and intended purpose); MAP 3.3 (scope) | J20: GV-1.6 actions (inventory); Value Chain and Component Integration | K20: LLM03 Supply Chain; ASI04 Agentic Supply Chain Vulnerabilities | L20: CC6.1 (asset inventory supports logical access); CC3.2; CC2.1
A21: compliance | B21: POS-02 | C21: AI Posture & Governance | D21: Risk classification | E21: GRC-02 Risk Management Program; GRC-10 AI Impact Assessment; TVM-12 Threat Analysis and Modelling | F21: Art. 6 classification rules; Art. 9 risk management system; Art. 27 fundamental rights impact assessment (deployers, where it applies) | G21: 6.1.2 AI risk assessment; 6.1.4 and 8.4 AI system impact assessment; A.5.2 AI system impact assessment process | H21: Threat model across the ATLAS tactics (AML.TA0004 Initial Access through AML.TA0011 Impact); AML.M0035 AI Red Team at High and Severe | I21: MAP 1.5 (risk tolerance); MAP 5.1 (likelihood and magnitude); MEASURE 1.1; MANAGE 1.2 (prioritization) | J21: MP-5.1 actions; GV-1.3 actions (risk tolerance); all 12 GenAI risks are candidates at classification | K21: Risk-based scoping across LLM01 to LLM10; ASI01 to ASI10 when agentic | L21: CC3.1, CC3.2, CC3.4 (risk assessment and changes)
A22: compliance | B22: POS-03 | C22: AI Posture & Governance | D22: Approval obtained | E22: GRC-01 Governance Program Policy; GRC-06 Governance Responsibility Model; UEM-02 Application and Service Approval; CCC-04 Change Authorization | F22: Art. 26(1) deployers use the system under appropriate technical and organizational measures; Art. 17 quality management (providers) | G22: A.3.2 AI roles and responsibilities; A.6.2.5 AI system deployment; 5.3 organizational roles | H22: AML.M0021 Generative AI Guidelines (approved use is written down) | I22: GOVERN 1.4 (transparent risk management process); GOVERN 2.1 (roles); MANAGE 1.1 | J22: GV-1.4 actions; GV-2.1 actions | K22: LLM06 Excessive Agency (approved scope); ASI03 Identity and Privilege Abuse (approval before privilege) | L22: CC5.1, CC5.3 (policies and procedures); CC8.1 (authorization)
A23: compliance | B23: POS-04 | C23: AI Posture & Governance | D23: Policy alignment | E23: GRC-09 Acceptable Use of the AI Service; HRS-15 AI Acceptable Use; HRS-02 Acceptable Use of Technology | F23: Art. 4 AI literacy; Art. 26 deployer obligations (use per instructions, assign oversight) | G23: A.2.2 AI policy; A.2.3 Alignment with other organizational policies; A.9.2 Processes for responsible use | H23: AML.M0021 Generative AI Guidelines; AML.M0018 User Training | I23: GOVERN 1.1 (legal and regulatory requirements); GOVERN 1.2 (trustworthy characteristics in policy); GOVERN 2.2 (training) | J23: GV-1.2 actions (policies for GenAI use); Human-AI Configuration | K23: ASI09 Human-Agent Trust Exploitation (user guidance); LLM02 (what users may share) | L23: CC1.1 (integrity and ethical values); CC1.4; CC2.2 (internal communication)
A24: compliance | B24: POS-05 | C24: AI Posture & Governance | D24: Owner assignment | E24: GRC-06 Governance Responsibility Model; DSP-06 Data Ownership and Stewardship; STA-05 SSRM Control Ownership | F24: Art. 26(2) deployers assign human oversight to competent, authorized persons; Art. 17 accountability within the QMS | G24: A.3.2 AI roles and responsibilities; 5.3 organizational roles | H24: No technique. A named owner operates the mitigations (AML.M0019 through AML.M0024) and answers for them | I24: GOVERN 2.1 (roles and responsibilities documented); GOVERN 2.3 (executive accountability); MAP 1.2 | J24: GV-2.1 actions (roles, including GenAI incident response roles) | K24: ASI10 Rogue Agents (someone answers for the agent); ASI03 | L24: CC1.3 (structures, reporting lines, authorities); CC2.2
A25: compliance | B25: POS-06 | C25: AI Posture & Governance | D25: Vendor assessment | E25: STA-01 Supply Chain Risk Management Policy; STA-09 Supply Chain Risk Management; STA-12 Supply Chain Compliance Assessment; STA-15 Supply Chain Data Security Assessment; A&A-02 Independent Assessments | F25: Art. 25 responsibilities along the AI value chain (written agreements); Art. 53 GPAI provider documentation to downstream providers; Art. 26 deployers rely on provider instructions (Art. 13) | G25: A.10.2 Allocating responsibilities; A.10.3 Suppliers | H25: AML.T0010 AI Supply Chain Compromise (.001 AI Software, .003 Model); AML.M0014 Verify AI Artifacts; AML.M0023 AI Bill of Materials | I25: GOVERN 6.1 (third-party risk policies); GOVERN 6.2 (contingency for third-party failures); MAP 4.1; MAP 4.2 | J25: GV-6.1 actions; GV-6.2 actions; Value Chain and Component Integration | K25: LLM03 Supply Chain; ASI04 Agentic Supply Chain Vulnerabilities | L25: CC9.2 (vendor and business partner risk); CC3.2
A26: compliance | B26: POS-07 | C26: AI Posture & Governance | D26: Compliance mapping | E26: GRC-07 Information System Regulatory Mapping; A&A-04 Requirements Compliance | F26: Art. 6 (is the use high-risk); Art. 26 and Art. 27 (deployer duties and impact assessment); Art. 50 (transparency duties) | G26: 4.2 Understanding the needs and expectations of interested parties; A.2.2 AI policy; A.8.3 External reporting | H26: No technique. The matrix shows which regulatory control each ATLAS mitigation serves | I26: GOVERN 1.1 (legal and regulatory requirements understood and managed); MAP 1.1 | J26: GV-1.1 actions (align GenAI use with applicable law) | K26: Cross-cutting: the LLM and Agentic lists are the control lenses this map cites | L26: CC1.1; CC2.3 (external communication); CC3.1 (objectives include compliance)
A27: compliance | B27: POS-08 | C27: AI Posture & Governance | D27: Data residency review | E27: DSP-19 Data Location; DSP-10 Sensitive Data Transfer; STA-10 Primary Service and Contractual Agreement | F27: Art. 22 authorized representatives for non-EU providers; residency and transfer rules sit in GDPR Chapter V, outside the AI Act | G27: A.7.3 Acquisition of data; A.10.3 Suppliers; A.7.5 Data provenance | H27: AML.M0005 Control Access to AI Models and Data at Rest; AML.M0019 Control Access to AI Models and Data in Production | I27: MAP 4.1 (legal risks of third-party components); GOVERN 1.1; MANAGE 3.1 | J27: MP-4.1 actions; Data Privacy | K27: LLM02 Sensitive Information Disclosure (where prompts and data land); LLM03 | L27: C1.1 (confidential information identified); CC6.7 (transmission); P4.1
A28: compliance | B28: RUN-01 | C28: Runtime Protection & Guardrails | D28: Input validation | E28: AIS-08 Input Validation; AIS-15 Prompt Differentiation; TVM-11 Guardrails; LOG-14 Input Monitoring | F28: Art. 15(5) cybersecurity: resilience against attempts to alter use or behavior, including attacks specific to AI; Art. 15(1) robustness | G28: A.6.2.4 AI system verification and validation; A.6.2.6 AI system operation and monitoring | H28: AML.T0051 LLM Prompt Injection (.000 Direct, .001 Indirect, .002 Triggered); AML.T0054 LLM Jailbreak; AML.T0068 LLM Prompt Obfuscation; AML.T0093 Prompt Infiltration via Public-Facing Application; AML.M0020 Generative AI Guardrails; AML.M0033 Input and Output Validation for AI Agent Components | I28: MEASURE 2.7 (security and resilience); MEASURE 2.5 (validity and reliability); MANAGE 2.2 | J28: MS-2.7 actions (prompt injection, security testing); Information Security | K28: LLM01 Prompt Injection; LLM07 System Prompt Leakage; ASI01 Agent Goal Hijack | L28: CC6.6 (boundary protection); CC6.8; PI1.2 (inputs)
A29: compliance | B29: RUN-02 | C29: Runtime Protection & Guardrails | D29: Output filtering | E29: AIS-09 Output Validation; LOG-15 Output Monitoring; TVM-11 Guardrails; IAM-18 Output Modification and Special Authorization | F29: Art. 15(1) accuracy and robustness; Art. 15(4) feedback loops; Art. 50(1) people told they are dealing with AI | G29: A.6.2.6 AI system operation and monitoring; A.8.2 System documentation and information for users; A.9.3 Objectives for responsible use | H29: AML.T0057 LLM Data Leakage; AML.T0077 LLM Response Rendering; AML.T0067 LLM Trusted Output Components Manipulation; AML.T0102 Generate Malicious Commands; AML.M0020 Generative AI Guardrails; AML.M0033 Input and Output Validation | I29: MEASURE 2.6 (safety); MEASURE 2.10 (privacy); MANAGE 2.2; MANAGE 4.1 | J29: MS-2.6 actions; MS-2.10 actions; Dangerous, Violent, or Hateful Content; Data Privacy; Confabulation | K29: LLM05 Improper Output Handling; LLM02 Sensitive Information Disclosure; LLM09 Misinformation | L29: PI1.3, PI1.4 (processing and outputs); C1.1; CC6.7
A30: compliance | B30: RUN-03 | C30: Runtime Protection & Guardrails | D30: Rate limiting (per user) | E30: AIS-10 API Security; I&S-02 Capacity and Resource Planning; TVM-11 Guardrails | F30: Art. 15(1) robustness and resilience; Art. 15(5) | G30: A.4.5 System and computing resources; A.6.2.6 | H30: AML.T0034 Cost Harvesting (.000 Excessive Queries); AML.T0029 Denial of AI Service; AML.T0024 Exfiltration via AI Inference API; AML.M0004 Limit AI Service Query Volume and Rate | I30: MEASURE 2.7; MANAGE 2.2; MAP 3.2 (costs) | J30: MS-2.7 actions; Information Security | K30: LLM10 Unbounded Consumption | L30: A1.1 (capacity); CC6.1; CC7.2
... A84: compliance | B84: SUP-13 | C84: AI Supply Chain | D84: Agent action attestation | E84: LOG-11 Transaction/Activity Logging; IAM-12 Safeguard Logs Integrity; LOG-02 Audit Logs Protection; IAM-19 Agent Access Restriction | F84: Art. 12 record-keeping (traceability); Art. 14; Art. 19 | G84: A.6.2.8 AI system recording of event logs; A.6.2.6; A.8.4 | H84: AML.M0024 AI Telemetry Logging; AML.M0029 Human In-the-Loop for AI Agent Actions; AML.M0013 Code Signing; non-repudiation against AML.T0074 Masquerading, AML.T0101 and AML.T0053 | I84: MEASURE 2.8 (accountability); MANAGE 4.1 | J84: MS-2.8 actions; MG-4.1 actions | K84: ASI10 Rogue Agents; ASI03; ASI07; LLM06 | L84: CC7.2; CC4.1; CC6.1
A86: 3. OWASP quick reference
A87: The LLM Top 10 applies to any model-backed application. Add the Agentic Top 10 when the agentic flag is set.
A88: ID | B88: Risk | E88: Key guardrails | H88: What it is
A89: LLM01 | B89: Prompt Injection | E89: RUN-01, RUN-05, RUN-06, SUP-11 | H89: Direct or indirect manipulation of prompts to change behavior or bypass controls
A90: LLM02 | B90: Sensitive Information Disclosure | E90: DAT-01, DAT-02, DAT-06, RUN-02, RUN-08 | H90: PII, secrets or confidential data leaving through outputs, logs or memory
A91: LLM03 | B91: Supply Chain | E91: POS-06, SUP-01, SUP-07, SUP-08, SUP-09 | H91: Compromised models, datasets, packages, plugins or MCP servers
A92: LLM04 | B92: Data and Model Poisoning | E92: SUP-04, SUP-07, SUP-10, SUP-12, OBS-05 | H92: Manipulated training, fine-tuning or retrieval data that corrupts behavior
A93: LLM05 | B93: Improper Output Handling | E93: RUN-02, RUN-05, NHI-11 | H93: Model output passed to downstream systems without validation
A94: LLM06 | B94: Excessive Agency | E94: NHI-01, NHI-06, NHI-07, NHI-09, OBS-08 | H94: Agents with more permissions, autonomy or tools than the task needs
A95: LLM07 | B95: System Prompt Leakage | E95: SUP-11, RUN-01, NHI-02 | H95: Exposure of system prompts, instructions or embedded secrets
A96: LLM08 | B96: Vector and Embedding Weaknesses | E96: SUP-10, SUP-12, DAT-03, NHI-12 | H96: RAG and embedding stores poisoned, over-shared or inverted
A97: LLM09 | B97: Misinformation | E97: RUN-02, OBS-05, OBS-07, DAT-09 | H97: Hallucinated or misleading output acted on as fact
A98: LLM10 | B98: Unbounded Consumption | E98: RUN-03, RUN-04, SHA-04, NHI-08 | H98: Resource exhaustion, cost abuse and model extraction through volume
A99: ASI01 | B99: Agent Goal Hijack | E99: RUN-01, NHI-06, SUP-11, OBS-06 | H99: The agent's objective or plan is redirected, usually through injected input
... A108: ASI10 | B108: Rogue Agents | E108: OBS-08, NHI-08, NHI-09, SUP-13 | H108: An agent operating outside policy through design failure, drift or compromise
A110: 4. EU AI Act application dates
A111: As amended by the 2026 Digital Omnibus. Confirm the current dates before relying on them.
A112: Date | C112: What applies
A113: 2 February 2025 | C113: Prohibited practices (Art. 5) and AI literacy (Art. 4) apply
A114: 2 August 2025 | C114: GPAI model obligations (Art. 53 to 55) apply; governance bodies in place
A115: 2 August 2026 | C115: Transparency duties (Art. 50) apply; the general application date for most of the Act
A116: 2 December 2026 | C116: End of the marking grace period for generative systems already on the market; new Art. 5 prohibition transition ends
A117: 2 December 2027 | C117: Annex III high-risk obligations apply (moved from 2 August 2026 by the 2026 Digital Omnibus)
A118: 2 August 2028 | C118: Annex I high-risk obligations (AI in regulated products) apply (moved from 2 August 2027)

Sheet Lists
A1: Pick lists for the data validations on the other tabs. Edit a list here to change the options offered.
B2: Every AI tool, feature and agent staff or systems use | C2: Internal users only | D2: No connection | E2: Answers and generates only, no actions | F2: No, in writing | G2: No | H2: On by default for everyone | I2: Prompts, responses and tool calls | J2: Our SIEM
B3: Purchased AI products and vendor AI features only | C3: Customers, partners or the public | D3: People sign in and type or upload | E3: Takes actions with a person approving each one | F3: No, by a setting we control | G3: Yes, an NDA | H3: On by default, admins can switch it off | I3: Some of those | J3: A log platform, not the SIEM
B4: Internal builds only | C4: Not sure | D4: Reads our data through an API, connector or index | E4: Takes actions on its own inside limits | F4: Yes | G4: Yes, a named-person login | H4: Off until an admin enables it | I4: None yet | J4: Application logs only
B5: Other (describe below) | D5: Reads and writes to our systems | E5: Takes actions on its own without limits | F5: Unknown | G5: Yes, a no-AI clause | H5: Not sure | I5: Not sure | J5: Not sure
D6: Privileged or infrastructure access | E6: Not sure | F6: Not applicable | G6: Not sure | H6: Not applicable
